Workbook

Sheet 概要
A1: クリーンルーム事実票：取り込み結果の概要
A2: 作成：2026-10-31（hm-cmed/cleanroom-facts の data/ から作成。件数は数式で数えています）
A4: ■ 全体
A5: カード（廃止を含む） | B5: =COUNTA(カード一覧!A2:A3170) -> 3169
A6: 有効なカード | B6: =COUNTIF(カード一覧!N2:N3170,"<>retired") -> 3136
A7: 廃止したカード | B7: =COUNTIF(カード一覧!N2:N3170,"retired") -> 33
A8: 専門医の監修済み（verified_expert） | B8: =COUNTIF(カード一覧!N2:N3170,"verified_expert") -> 0
A9: 出典 | B9: =COUNTA(出典一覧!A2:A1840) -> 1839
A10: 出題基準の項目 | B10: =COUNTA(出題基準の網羅!D2:D1483) -> 1482
A11: カードのある項目 | B11: =COUNTIF(出題基準の網羅!H2:H1483,"あり") -> 1174
A12: 項目の網羅率 | B12: =B11/B10 -> 0.79217274
A14: ■ 章ごとの出題基準の網羅
A15: 章 | B15: 章の名前 | C15: 項目 | D15: レベル a | E15: カードのある項目 | F15: 網羅率 | G15: レベル a でカードのない項目
A16: Ⅰ | B16: 先天異常、周産期の異常、成長・発達の異常 | C16: =COUNTIF(出題基準の網羅!$A$2:$A$1483,A16) -> 82 | D16: =COUNTIFS(出題基準の網羅!$A$2:$A$1483,A16,出題基準の網羅!$F$2:$F$1483,"a") -> 20 | E16: =COUNTIFS(出題基準の網羅!$A$2:$A$1483,A16,出題基準の網羅!$H$2:$H$1483,"あり") -> 4 | F16: =IF(C16=0,0,E16/C16) -> 0.048780488 | G16: =COUNTIFS(出題基準の網羅!$A$2:$A$1483,A16,出題基準の網羅!$F$2:$F$1483,"a",出題基準の網羅!$H$2:$H$1483,"なし") -> 19
A17: Ⅱ | B17: 精神・心身医学的疾患 | C17: =COUNTIF(出題基準の網羅!$A$2:$A$1483,A17) -> 54 | D17: =COUNTIFS(出題基準の網羅!$A$2:$A$1483,A17,出題基準の網羅!$F$2:$F$1483,"a") -> 22 | E17: =COUNTIFS(出題基準の網羅!$A$2:$A$1483,A17,出題基準の網羅!$H$2:$H$1483,"あり") -> 4 | F17: =IF(C17=0,0,E17/C17) -> 0.074074074 | G17: =COUNTIFS(出題基準の網羅!$A$2:$A$1483,A17,出題基準の網羅!$F$2:$F$1483,"a",出題基準の網羅!$H$2:$H$1483,"なし") -> 19
A18: Ⅲ | B18: 皮膚・頭頸部疾患 | C18: =COUNTIF(出題基準の網羅!$A$2:$A$1483,A18) -> 257 | D18: =COUNTIFS(出題基準の網羅!$A$2:$A$1483,A18,出題基準の網羅!$F$2:$F$1483,"a") -> 96 | E18: =COUNTIFS(出題基準の網羅!$A$2:$A$1483,A18,出題基準の網羅!$H$2:$H$1483,"あり") -> 248 | F18: =IF(C18=0,0,E18/C18) -> 0.96498054 | G18: =COUNTIFS(出題基準の網羅!$A$2:$A$1483,A18,出題基準の網羅!$F$2:$F$1483,"a",出題基準の網羅!$H$2:$H$1483,"なし") -> 0
A19: Ⅳ | B19: 呼吸器・胸壁・縦隔疾患 | C19: =COUNTIF(出題基準の網羅!$A$2:$A$1483,A19) -> 86 | D19: =COUNTIFS(出題基準の網羅!$A$2:$A$1483,A19,出題基準の網羅!$F$2:$F$1483,"a") -> 41 | E19: =COUNTIFS(出題基準の網羅!$A$2:$A$1483,A19,出題基準の網羅!$H$2:$H$1483,"あり") -> 86 | F19: =IF(C19=0,0,E19/C19) -> 1 | G19: =COUNTIFS(出題基準の網羅!$A$2:$A$1483,A19,出題基準の網羅!$F$2:$F$1483,"a",出題基準の網羅!$H$2:$H$1483,"なし") -> 0
A20: Ⅴ | B20: 心臓・脈管疾患 | C20: =COUNTIF(出題基準の網羅!$A$2:$A$1483,A20) -> 85 | D20: =COUNTIFS(出題基準の網羅!$A$2:$A$1483,A20,出題基準の網羅!$F$2:$F$1483,"a") -> 51 | E20: =COUNTIFS(出題基準の網羅!$A$2:$A$1483,A20,出題基準の網羅!$H$2:$H$1483,"あり") -> 73 | F20: =IF(C20=0,0,E20/C20) -> 0.85882353 | G20: =COUNTIFS(出題基準の網羅!$A$2:$A$1483,A20,出題基準の網羅!$F$2:$F$1483,"a",出題基準の網羅!$H$2:$H$1483,"なし") -> 5
A21: Ⅵ | B21: 消化器・腹壁・腹膜疾患 | C21: =COUNTIF(出題基準の網羅!$A$2:$A$1483,A21) -> 134 | D21: =COUNTIFS(出題基準の網羅!$A$2:$A$1483,A21,出題基準の網羅!$F$2:$F$1483,"a") -> 66 | E21: =COUNTIFS(出題基準の網羅!$A$2:$A$1483,A21,出題基準の網羅!$H$2:$H$1483,"あり") -> 65 | F21: =IF(C21=0,0,E21/C21) -> 0.48507463 | G21: =COUNTIFS(出題基準の網羅!$A$2:$A$1483,A21,出題基準の網羅!$F$2:$F$1483,"a",出題基準の網羅!$H$2:$H$1483,"なし") -> 21
A22: Ⅶ | B22: 血液・造血器疾患 | C22: =COUNTIF(出題基準の網羅!$A$2:$A$1483,A22) -> 62 | D22: =COUNTIFS(出題基準の網羅!$A$2:$A$1483,A22,出題基準の網羅!$F$2:$F$1483,"a") -> 23 | E22: =COUNTIFS(出題基準の網羅!$A$2:$A$1483,A22,出題基準の網羅!$H$2:$H$1483,"あり") -> 62 | F22: =IF(C22=0,0,E22/C22) -> 1 | G22: =COUNTIFS(出題基準の網羅!$A$2:$A$1483,A22,出題基準の網羅!$F$2:$F$1483,"a",出題基準の網羅!$H$2:$H$1483,"なし") -> 0
A23: Ⅷ | B23: 腎・泌尿器・生殖器疾患 | C23: =COUNTIF(出題基準の網羅!$A$2:$A$1483,A23) -> 177 | D23: =COUNTIFS(出題基準の網羅!$A$2:$A$1483,A23,出題基準の網羅!$F$2:$F$1483,"a") -> 85 | E23: =COUNTIFS(出題基準の網羅!$A$2:$A$1483,A23,出題基準の網羅!$H$2:$H$1483,"あり") -> 175 | F23: =IF(C23=0,0,E23/C23) -> 0.98870056 | G23: =COUNTIFS(出題基準の網羅!$A$2:$A$1483,A23,出題基準の網羅!$F$2:$F$1483,"a",出題基準の網羅!$H$2:$H$1483,"なし") -> 0
A24: Ⅸ | B24: 神経・運動器疾患 | C24: =COUNTIF(出題基準の網羅!$A$2:$A$1483,A24) -> 228 | D24: =COUNTIFS(出題基準の網羅!$A$2:$A$1483,A24,出題基準の網羅!$F$2:$F$1483,"a") -> 87 | E24: =COUNTIFS(出題基準の網羅!$A$2:$A$1483,A24,出題基準の網羅!$H$2:$H$1483,"あり") -> 228 | F24: =IF(C24=0,0,E24/C24) -> 1 | G24: =COUNTIFS(出題基準の網羅!$A$2:$A$1483,A24,出題基準の網羅!$F$2:$F$1483,"a",出題基準の網羅!$H$2:$H$1483,"なし") -> 0
A25: Ⅹ | B25: 内分泌・代謝・栄養・乳腺疾患 | C25: =COUNTIF(出題基準の網羅!$A$2:$A$1483,A25) -> 100 | D25: =COUNTIFS(出題基準の網羅!$A$2:$A$1483,A25,出題基準の網羅!$F$2:$F$1483,"a") -> 30 | E25: =COUNTIFS(出題基準の網羅!$A$2:$A$1483,A25,出題基準の網羅!$H$2:$H$1483,"あり") -> 99 | F25: =IF(C25=0,0,E25/C25) -> 0.99 | G25: =COUNTIFS(出題基準の網羅!$A$2:$A$1483,A25,出題基準の網羅!$F$2:$F$1483,"a",出題基準の網羅!$H$2:$H$1483,"なし") -> 0
A26: Ⅺ | B26: アレルギー性疾患、膠原病、免疫病 | C26: =COUNTIF(出題基準の網羅!$A$2:$A$1483,A26) -> 65 | D26: =COUNTIFS(出題基準の網羅!$A$2:$A$1483,A26,出題基準の網羅!$F$2:$F$1483,"a") -> 30 | E26: =COUNTIFS(出題基準の網羅!$A$2:$A$1483,A26,出題基準の網羅!$H$2:$H$1483,"あり") -> 41 | F26: =IF(C26=0,0,E26/C26) -> 0.63076923 | G26: =COUNTIFS(出題基準の網羅!$A$2:$A$1483,A26,出題基準の網羅!$F$2:$F$1483,"a",出題基準の網羅!$H$2:$H$1483,"なし") -> 5
A27: Ⅻ | B27: 感染性疾患 | C27: =COUNTIF(出題基準の網羅!$A$2:$A$1483,A27) -> 87 | D27: =COUNTIFS(出題基準の網羅!$A$2:$A$1483,A27,出題基準の網羅!$F$2:$F$1483,"a") -> 55 | E27: =COUNTIFS(出題基準の網羅!$A$2:$A$1483,A27,出題基準の網羅!$H$2:$H$1483,"あり") -> 87 | F27: =IF(C27=0,0,E27/C27) -> 1 | G27: =COUNTIFS(出題基準の網羅!$A$2:$A$1483,A27,出題基準の網羅!$F$2:$F$1483,"a",出題基準の網羅!$H$2:$H$1483,"なし") -> 0
A28: ⅩⅢ | B28: 生活環境因子・職業性因子による疾患 | C28: =COUNTIF(出題基準の網羅!$A$2:$A$1483,A28) -> 65 | D28: =COUNTIFS(出題基準の網羅!$A$2:$A$1483,A28,出題基準の網羅!$F$2:$F$1483,"a") -> 37 | E28: =COUNTIFS(出題基準の網羅!$A$2:$A$1483,A28,出題基準の網羅!$H$2:$H$1483,"あり") -> 2 | F28: =IF(C28=0,0,E28/C28) -> 0.030769231 | G28: =COUNTIFS(出題基準の網羅!$A$2:$A$1483,A28,出題基準の網羅!$F$2:$F$1483,"a",出題基準の網羅!$H$2:$H$1483,"なし") -> 35
A29: 計 | C29: =SUM(C16:C28) -> 1482 | D29: =SUM(D16:D28) -> 643 | E29: =SUM(E16:E28) -> 1174 | F29: =IF(C29=0,0,E29/C29) -> 0.79217274 | G29: =SUM(G16:G28) -> 104
A31: ■ 分野・接頭辞ごとの件数
A32: 分野 | B32: 接頭辞 | C32: 範囲 | D32: 有効 | E32: 廃止 | F32: 監修済み | G32: OPEN | H32: RESTRICTED | I32: GOV_JP | J32: GOV_US | K32: UNKNOWN
A33: 消化器 | B33: HP | C33: H. pylori関連疾患 | D33: =COUNTIFS(カード一覧!$C$2:$C$3170,B33,カード一覧!$N$2:$N$3170,"<>retired") -> 20 | E33: =COUNTIFS(カード一覧!$C$2:$C$3170,B33,カード一覧!$N$2:$N$3170,"retired") -> 0 | F33: =COUNTIFS(カード一覧!$C$2:$C$3170,B33,カード一覧!$N$2:$N$3170,"verified_expert") -> 0 | G33: =COUNTIFS(カード一覧!$C$2:$C$3170,B33,カード一覧!$N$2:$N$3170,"<>retired",カード一覧!$M$2:$M$3170,"OPEN") -> 10 | H33: =COUNTIFS(カード一覧!$C$2:$C$3170,B33,カード一覧!$N$2:$N$3170,"<>retired",カード一覧!$M$2:$M$3170,"RESTRICTED") -> 6 | I33: =COUNTIFS(カード一覧!$C$2:$C$3170,B33,カード一覧!$N$2:$N$3170,"<>retired",カード一覧!$M$2:$M$3170,"GOV_JP") -> 0 | J33: =COUNTIFS(カード一覧!$C$2:$C$3170,B33,カード一覧!$N$2:$N$3170,"<>retired",カード一覧!$M$2:$M$3170,"GOV_US") -> 0 | K33: =COUNTIFS(カード一覧!$C$2:$C$3170,B33,カード一覧!$N$2:$N$3170,"<>retired",カード一覧!$M$2:$M$3170,"UNKNOWN") -> 4
A34: 消化器 | B34: UG | C34: 上部消化管出血 | D34: =COUNTIFS(カード一覧!$C$2:$C$3170,B34,カード一覧!$N$2:$N$3170,"<>retired") -> 18 | E34: =COUNTIFS(カード一覧!$C$2:$C$3170,B34,カード一覧!$N$2:$N$3170,"retired") -> 0 | F34: =COUNTIFS(カード一覧!$C$2:$C$3170,B34,カード一覧!$N$2:$N$3170,"verified_expert") -> 0 | G34: =COUNTIFS(カード一覧!$C$2:$C$3170,B34,カード一覧!$N$2:$N$3170,"<>retired",カード一覧!$M$2:$M$3170,"OPEN") -> 2 | H34: =COUNTIFS(カード一覧!$C$2:$C$3170,B34,カード一覧!$N$2:$N$3170,"<>retired",カード一覧!$M$2:$M$3170,"RESTRICTED") -> 10 | I34: =COUNTIFS(カード一覧!$C$2:$C$3170,B34,カード一覧!$N$2:$N$3170,"<>retired",カード一覧!$M$2:$M$3170,"GOV_JP") -> 0 | J34: =COUNTIFS(カード一覧!$C$2:$C$3170,B34,カード一覧!$N$2:$N$3170,"<>retired",カード一覧!$M$2:$M$3170,"GOV_US") -> 0 | K34: =COUNTIFS(カード一覧!$C$2:$C$3170,B34,カード一覧!$N$2:$N$3170,"<>retired",カード一覧!$M$2:$M$3170,"UNKNOWN") -> 6
A35: 消化器 | B35: ES | C35: 食道 | D35: =COUNTIFS(カード一覧!$C$2:$C$3170,B35,カード一覧!$N$2:$N$3170,"<>retired") -> 89 | E35: =COUNTIFS(カード一覧!$C$2:$C$3170,B35,カード一覧!$N$2:$N$3170,"retired") -> 4 | F35: =COUNTIFS(カード一覧!$C$2:$C$3170,B35,カード一覧!$N$2:$N$3170,"verified_expert") -> 0 | G35: =COUNTIFS(カード一覧!$C$2:$C$3170,B35,カード一覧!$N$2:$N$3170,"<>retired",カード一覧!$M$2:$M$3170,"OPEN") -> 30 | H35: =COUNTIFS(カード一覧!$C$2:$C$3170,B35,カード一覧!$N$2:$N$3170,"<>retired",カード一覧!$M$2:$M$3170,"RESTRICTED") -> 47 | I35: =COUNTIFS(カード一覧!$C$2:$C$3170,B35,カード一覧!$N$2:$N$3170,"<>retired",カード一覧!$M$2:$M$3170,"GOV_JP") -> 2 | J35: =COUNTIFS(カード一覧!$C$2:$C$3170,B35,カード一覧!$N$2:$N$3170,"<>retired",カード一覧!$M$2:$M$3170,"GOV_US") -> 0 | K35: =COUNTIFS(カード一覧!$C$2:$C$3170,B35,カード一覧!$N$2:$N$3170,"<>retired",カード一覧!$M$2:$M$3170,"UNKNOWN") -> 10
A36: 消化器 | B36: GD | C36: 胃・十二指腸 | D36: =COUNTIFS(カード一覧!$C$2:$C$3170,B36,カード一覧!$N$2:$N$3170,"<>retired") -> 94 | E36: =COUNTIFS(カード一覧!$C$2:$C$3170,B36,カード一覧!$N$2:$N$3170,"retired") -> 1 | F36: =COUNTIFS(カード一覧!$C$2:$C$3170,B36,カード一覧!$N$2:$N$3170,"verified_expert") -> 0 | G36: =COUNTIFS(カード一覧!$C$2:$C$3170,B36,カード一覧!$N$2:$N$3170,"<>retired",カード一覧!$M$2:$M$3170,"OPEN") -> 71 | H36: =COUNTIFS(カード一覧!$C$2:$C$3170,B36,カード一覧!$N$2:$N$3170,"<>retired",カード一覧!$M$2:$M$3170,"RESTRICTED") -> 15 | I36: =COUNTIFS(カード一覧!$C$2:$C$3170,B36,カード一覧!$N$2:$N$3170,"<>retired",カード一覧!$M$2:$M$3170,"GOV_JP") -> 5 | J36: =COUNTIFS(カード一覧!$C$2:$C$3170,B36,カード一覧!$N$2:$N$3170,"<>retired",カード一覧!$M$2:$M$3170,"GOV_US") -> 1 | K36: =COUNTIFS(カード一覧!$C$2:$C$3170,B36,カード一覧!$N$2:$N$3170,"<>retired",カード一覧!$M$2:$M$3170,"UNKNOWN") -> 2
A37: 消化器 | B37: IN | C37: 小腸・大腸 | D37: =COUNTIFS(カード一覧!$C$2:$C$3170,B37,カード一覧!$N$2:$N$3170,"<>retired") -> 89 | E37: =COUNTIFS(カード一覧!$C$2:$C$3170,B37,カード一覧!$N$2:$N$3170,"retired") -> 0 | F37: =COUNTIFS(カード一覧!$C$2:$C$3170,B37,カード一覧!$N$2:$N$3170,"verified_expert") -> 0 | G37: =COUNTIFS(カード一覧!$C$2:$C$3170,B37,カード一覧!$N$2:$N$3170,"<>retired",カード一覧!$M$2:$M$3170,"OPEN") -> 39 | H37: =COUNTIFS(カード一覧!$C$2:$C$3170,B37,カード一覧!$N$2:$N$3170,"<>retired",カード一覧!$M$2:$M$3170,"RESTRICTED") -> 20 | I37: =COUNTIFS(カード一覧!$C$2:$C$3170,B37,カード一覧!$N$2:$N$3170,"<>retired",カード一覧!$M$2:$M$3170,"GOV_JP") -> 13 | J37: =COUNTIFS(カード一覧!$C$2:$C$3170,B37,カード一覧!$N$2:$N$3170,"<>retired",カード一覧!$M$2:$M$3170,"GOV_US") -> 11 | K37: =COUNTIFS(カード一覧!$C$2:$C$3170,B37,カード一覧!$N$2:$N$3170,"<>retired",カード一覧!$M$2:$M$3170,"UNKNOWN") -> 6
A38: 消化器 | B38: LV | C38: 肝 | D38: =COUNTIFS(カード一覧!$C$2:$C$3170,B38,カード一覧!$N$2:$N$3170,"<>retired") -> 104 | E38: =COUNTIFS(カード一覧!$C$2:$C$3170,B38,カード一覧!$N$2:$N$3170,"retired") -> 0 | F38: =COUNTIFS(カード一覧!$C$2:$C$3170,B38,カード一覧!$N$2:$N$3170,"verified_expert") -> 0 | G38: =COUNTIFS(カード一覧!$C$2:$C$3170,B38,カード一覧!$N$2:$N$3170,"<>retired",カード一覧!$M$2:$M$3170,"OPEN") -> 34 | H38: =COUNTIFS(カード一覧!$C$2:$C$3170,B38,カード一覧!$N$2:$N$3170,"<>retired",カード一覧!$M$2:$M$3170,"RESTRICTED") -> 23 | I38: =COUNTIFS(カード一覧!$C$2:$C$3170,B38,カード一覧!$N$2:$N$3170,"<>retired",カード一覧!$M$2:$M$3170,"GOV_JP") -> 26 | J38: =COUNTIFS(カード一覧!$C$2:$C$3170,B38,カード一覧!$N$2:$N$3170,"<>retired",カード一覧!$M$2:$M$3170,"GOV_US") -> 17 | K38: =COUNTIFS(カード一覧!$C$2:$C$3170,B38,カード一覧!$N$2:$N$3170,"<>retired",カード一覧!$M$2:$M$3170,"UNKNOWN") -> 4
A39: 消化器 | B39: BP | C39: 胆・膵 | D39: =COUNTIFS(カード一覧!$C$2:$C$3170,B39,カード一覧!$N$2:$N$3170,"<>retired") -> 68 | E39: =COUNTIFS(カード一覧!$C$2:$C$3170,B39,カード一覧!$N$2:$N$3170,"retired") -> 0 | F39: =COUNTIFS(カード一覧!$C$2:$C$3170,B39,カード一覧!$N$2:$N$3170,"verified_expert") -> 0 | G39: =COUNTIFS(カード一覧!$C$2:$C$3170,B39,カード一覧!$N$2:$N$3170,"<>retired",カード一覧!$M$2:$M$3170,"OPEN") -> 0 | H39: =COUNTIFS(カード一覧!$C$2:$C$3170,B39,カード一覧!$N$2:$N$3170,"<>retired",カード一覧!$M$2:$M$3170,"RESTRICTED") -> 18 | I39: =COUNTIFS(カード一覧!$C$2:$C$3170,B39,カード一覧!$N$2:$N$3170,"<>retired",カード一覧!$M$2:$M$3170,"GOV_JP") -> 12 | J39: =COUNTIFS(カード一覧!$C$2:$C$3170,B39,カード一覧!$N$2:$N$3170,"<>retired",カード一覧!$M$2:$M$3170,"GOV_US") -> 12 | K39: =COUNTIFS(カード一覧!$C$2:$C$3170,B39,カード一覧!$N$2:$N$3170,"<>retired",カード一覧!$M$2:$M$3170,"UNKNOWN") -> 26
A40: 消化器 | B40: AB | C40: 腹膜・腹壁・急性腹症 | D40: =COUNTIFS(カード一覧!$C$2:$C$3170,B40,カード一覧!$N$2:$N$3170,"<>retired") -> 93 | E40: =COUNTIFS(カード一覧!$C$2:$C$3170,B40,カード一覧!$N$2:$N$3170,"retired") -> 0 | F40: =COUNTIFS(カード一覧!$C$2:$C$3170,B40,カード一覧!$N$2:$N$3170,"verified_expert") -> 0 | G40: =COUNTIFS(カード一覧!$C$2:$C$3170,B40,カード一覧!$N$2:$N$3170,"<>retired",カード一覧!$M$2:$M$3170,"OPEN") -> 24 | H40: =COUNTIFS(カード一覧!$C$2:$C$3170,B40,カード一覧!$N$2:$N$3170,"<>retired",カード一覧!$M$2:$M$3170,"RESTRICTED") -> 69 | I40: =COUNTIFS(カード一覧!$C$2:$C$3170,B40,カード一覧!$N$2:$N$3170,"<>retired",カード一覧!$M$2:$M$3170,"GOV_JP") -> 0 | J40: =COUNTIFS(カード一覧!$C$2:$C$3170,B40,カード一覧!$N$2:$N$3170,"<>retired",カード一覧!$M$2:$M$3170,"GOV_US") -> 0 | K40: =COUNTIFS(カード一覧!$C$2:$C$3170,B40,カード一覧!$N$2:$N$3170,"<>retired",カード一覧!$M$2:$M$3170,"UNKNOWN") -> 0
A41: 消化器 | B41: XS | C41: 症候・検査・栄養 | D41: =COUNTIFS(カード一覧!$C$2:$C$3170,B41,カード一覧!$N$2:$N$3170,"<>retired") -> 37 | E41: =COUNTIFS(カード一覧!$C$2:$C$3170,B41,カード一覧!$N$2:$N$3170,"retired") -> 0 | F41: =COUNTIFS(カード一覧!$C$2:$C$3170,B41,カード一覧!$N$2:$N$3170,"verified_expert") -> 0 | G41: =COUNTIFS(カード一覧!$C$2:$C$3170,B41,カード一覧!$N$2:$N$3170,"<>retired",カード一覧!$M$2:$M$3170,"OPEN") -> 7 | H41: =COUNTIFS(カード一覧!$C$2:$C$3170,B41,カード一覧!$N$2:$N$3170,"<>retired",カード一覧!$M$2:$M$3170,"RESTRICTED") -> 24 | I41: =COUNTIFS(カード一覧!$C$2:$C$3170,B41,カード一覧!$N$2:$N$3170,"<>retired",カード一覧!$M$2:$M$3170,"GOV_JP") -> 0 | J41: =COUNTIFS(カード一覧!$C$2:$C$3170,B41,カード一覧!$N$2:$N$3170,"<>retired",カード一覧!$M$2:$M$3170,"GOV_US") -> 0 | K41: =COUNTIFS(カード一覧!$C$2:$C$3170,B41,カード一覧!$N$2:$N$3170,"<>retired",カード一覧!$M$2:$M$3170,"UNKNOWN") -> 6
A42: 消化器 | B42: NG | C42: 神経消化器病 | D42: =COUNTIFS(カード一覧!$C$2:$C$3170,B42,カード一覧!$N$2:$N$3170,"<>retired") -> 240 | E42: =COUNTIFS(カード一覧!$C$2:$C$3170,B42,カード一覧!$N$2:$N$3170,"retired") -> 0 | F42: =COUNTIFS(カード一覧!$C$2:$C$3170,B42,カード一覧!$N$2:$N$3170,"verified_expert") -> 0 | G42: =COUNTIFS(カード一覧!$C$2:$C$3170,B42,カード一覧!$N$2:$N$3170,"<>retired",カード一覧!$M$2:$M$3170,"OPEN") -> 41 | H42: =COUNTIFS(カード一覧!$C$2:$C$3170,B42,カード一覧!$N$2:$N$3170,"<>retired",カード一覧!$M$2:$M$3170,"RESTRICTED") -> 155 | I42: =COUNTIFS(カード一覧!$C$2:$C$3170,B42,カード一覧!$N$2:$N$3170,"<>retired",カード一覧!$M$2:$M$3170,"GOV_JP") -> 9 | J42: =COUNTIFS(カード一覧!$C$2:$C$3170,B42,カード一覧!$N$2:$N$3170,"<>retired",カード一覧!$M$2:$M$3170,"GOV_US") -> 19 | K42: =COUNTIFS(カード一覧!$C$2:$C$3170,B42,カード一覧!$N$2:$N$3170,"<>retired",カード一覧!$M$2:$M$3170,"UNKNOWN") -> 16
A43: 循環器 | B43: AR | C43: 不整脈 | D43: =COUNTIFS(カード一覧!$C$2:$C$3170,B43,カード一覧!$N$2:$N$3170,"<>retired") -> 35 | E43: =COUNTIFS(カード一覧!$C$2:$C$3170,B43,カード一覧!$N$2:$N$3170,"retired") -> 0 | F43: =COUNTIFS(カード一覧!$C$2:$C$3170,B43,カード一覧!$N$2:$N$3170,"verified_expert") -> 0 | G43: =COUNTIFS(カード一覧!$C$2:$C$3170,B43,カード一覧!$N$2:$N$3170,"<>retired",カード一覧!$M$2:$M$3170,"OPEN") -> 15 | H43: =COUNTIFS(カード一覧!$C$2:$C$3170,B43,カード一覧!$N$2:$N$3170,"<>retired",カード一覧!$M$2:$M$3170,"RESTRICTED") -> 20 | I43: =COUNTIFS(カード一覧!$C$2:$C$3170,B43,カード一覧!$N$2:$N$3170,"<>retired",カード一覧!$M$2:$M$3170,"GOV_JP") -> 0 | J43: =COUNTIFS(カード一覧!$C$2:$C$3170,B43,カード一覧!$N$2:$N$3170,"<>retired",カード一覧!$M$2:$M$3170,"GOV_US") -> 0 | K43: =COUNTIFS(カード一覧!$C$2:$C$3170,B43,カード一覧!$N$2:$N$3170,"<>retired",カード一覧!$M$2:$M$3170,"UNKNOWN") -> 0
A44: 循環器 | B44: HF | C44: 心不全 | D44: =COUNTIFS(カード一覧!$C$2:$C$3170,B44,カード一覧!$N$2:$N$3170,"<>retired") -> 25 | E44: =COUNTIFS(カード一覧!$C$2:$C$3170,B44,カード一覧!$N$2:$N$3170,"retired") -> 0 | F44: =COUNTIFS(カード一覧!$C$2:$C$3170,B44,カード一覧!$N$2:$N$3170,"verified_expert") -> 0 | G44: =COUNTIFS(カード一覧!$C$2:$C$3170,B44,カード一覧!$N$2:$N$3170,"<>retired",カード一覧!$M$2:$M$3170,"OPEN") -> 0 | H44: =COUNTIFS(カード一覧!$C$2:$C$3170,B44,カード一覧!$N$2:$N$3170,"<>retired",カード一覧!$M$2:$M$3170,"RESTRICTED") -> 24 | I44: =COUNTIFS(カード一覧!$C$2:$C$3170,B44,カード一覧!$N$2:$N$3170,"<>retired",カード一覧!$M$2:$M$3170,"GOV_JP") -> 0 | J44: =COUNTIFS(カード一覧!$C$2:$C$3170,B44,カード一覧!$N$2:$N$3170,"<>retired",カード一覧!$M$2:$M$3170,"GOV_US") -> 0 | K44: =COUNTIFS(カード一覧!$C$2:$C$3170,B44,カード一覧!$N$2:$N$3170,"<>retired",カード一覧!$M$2:$M$3170,"UNKNOWN") -> 1
... A113: アレルギー・膠原病・免疫 | B113: VA | C113: 血管炎症候群とその関連疾患 | D113: =COUNTIFS(カード一覧!$C$2:$C$3170,B113,カード一覧!$N$2:$N$3170,"<>retired") -> 19 | E113: =COUNTIFS(カード一覧!$C$2:$C$3170,B113,カード一覧!$N$2:$N$3170,"retired") -> 0 | F113: =COUNTIFS(カード一覧!$C$2:$C$3170,B113,カード一覧!$N$2:$N$3170,"verified_expert") -> 0 | G113: =COUNTIFS(カード一覧!$C$2:$C$3170,B113,カード一覧!$N$2:$N$3170,"<>retired",カード一覧!$M$2:$M$3170,"OPEN") -> 0 | H113: =COUNTIFS(カード一覧!$C$2:$C$3170,B113,カード一覧!$N$2:$N$3170,"<>retired",カード一覧!$M$2:$M$3170,"RESTRICTED") -> 8 | I113: =COUNTIFS(カード一覧!$C$2:$C$3170,B113,カード一覧!$N$2:$N$3170,"<>retired",カード一覧!$M$2:$M$3170,"GOV_JP") -> 1 | J113: =COUNTIFS(カード一覧!$C$2:$C$3170,B113,カード一覧!$N$2:$N$3170,"<>retired",カード一覧!$M$2:$M$3170,"GOV_US") -> 0 | K113: =COUNTIFS(カード一覧!$C$2:$C$3170,B113,カード一覧!$N$2:$N$3170,"<>retired",カード一覧!$M$2:$M$3170,"UNKNOWN") -> 10
A114: 計 | D114: =SUM(D33:D113) -> 3136 | E114: =SUM(E33:E113) -> 33 | F114: =SUM(F33:F113) -> 0 | G114: =SUM(G33:G113) -> 519 | H114: =SUM(H33:H113) -> 1581 | I114: =SUM(I33:I113) -> 184 | J114: =SUM(J33:J113) -> 140 | K114: =SUM(K33:K113) -> 712

Sheet カード一覧
A1: ID | B1: 分野 | C1: 接頭辞 | D1: 主題（subdomain） | E1: 主張文 | F1: 地域 | G1: 出題基準（医学各論） | H1: コアカリ | I1: 出典番号 | J1: 出典 | K1: DOI | L1: PMID | M1: ライセンス区分 | N1: 状態 | O1: 置き換え先 | P1: 作成日 | Q1: 不確かさ（uncertainty）
A2: HP-001 | B2: 消化器 | C2: HP | E2: 2018〜2020年に日本国内で集めたH. pylori臨床分離株では、クラリスロマイシン耐性が35.5%、アモキシシリン耐性が2.7%、メトロニダゾール耐性が4.2%だった。 | F2: JP | G2: 医学各論 Ⅻ-2-B-⑧（ヘリコバクター・ピロリ感染症、a） | J2: Okimoto T et al. Helicobacter 2024;29:e13028 | K2: 10.1111/hel.13028 | M2: RESTRICTED | N2: draft | P2: 2026-10-10
A3: HP-002 | B3: 消化器 | C3: HP | E3: 日本の第III相二重盲検RCTでは、一次除菌（三剤）の除菌率がボノプラザン群92.6%、ランソプラゾール群75.9%だった。 | F3: JP | G3: 医学各論 Ⅻ-2-B-⑧（ヘリコバクター・ピロリ感染症、a） | J3: Murakami K et al. Gut 2016;65:1439-46 | K3: 10.1136/gutjnl-2015-311304 | L3: 26935876 | M3: UNKNOWN | N3: draft | P3: 2026-10-10 | Q3: DOI・PMIDはPubMedのコメント記事（PMID 27210791）とClinicalTrials.gov NCT04901663の文献リストで確認。ライセンスは要確認
A4: HP-003 | B4: 消化器 | C4: HP | E4: 同じRCTのCAM耐性株感染例では、除菌率がボノプラザン三剤で82.0%、ランソプラゾール三剤で40.0%だった（p<0.0001）。 | F4: JP | G4: 医学各論 Ⅻ-2-B-⑧（ヘリコバクター・ピロリ感染症、a） | J4: Murakami 2016 原著本文（PMC5036253、online supplementary table S1参照）; Frontiers Pharmacol 2018 (10.3389/fphar.2018.01560) | M4: UNKNOWN | N4: draft | P4: 2026-10-10 | Q4: 数値は原著本文で確認済み。ライセンスは要確認
A5: HP-004 | B5: 消化器 | C5: HP | E5: JSGE 2026は、一次除菌ではPPIよりボノプラザンを含む三剤療法を用いることを強く推奨している（エビデンスA、7件のRCTのメタ解析）。 | F5: JP | G5: 医学各論 Ⅻ-2-B-⑧（ヘリコバクター・ピロリ感染症、a） | J5: JSGE PUD GL 2026 | K5: 10.1007/s00535-026-02504-3 | M5: OPEN | N5: draft | P5: 2026-10-10
A6: HP-005 | B6: 消化器 | C6: HP | E6: JSGE 2026は、可能であれば一次除菌前にCAM感受性検査を行い、最も高い除菌率が見込めるレジメンを選ぶよう強く推奨している。 | F6: JP | G6: 医学各論 Ⅻ-2-B-⑧（ヘリコバクター・ピロリ感染症、a） | J6: JSGE PUD GL 2026 | K6: 10.1007/s00535-026-02504-3 | M6: OPEN | N6: draft | P6: 2026-10-10
A7: HP-006 | B7: 消化器 | C7: HP | E7: CAM感受性株にはVPZ＋AMPC＋CAMを、CAM耐性株にはPPIまたはVPZ＋AMPC＋MNZを用いることが推奨されている。 | F7: JP | G7: 医学各論 Ⅻ-2-B-⑧（ヘリコバクター・ピロリ感染症、a） | J7: JSGE PUD GL 2026 | K7: 10.1007/s00535-026-02504-3 | M7: OPEN | N7: draft | P7: 2026-10-10
A8: HP-007 | B8: 消化器 | C8: HP | E8: 日本の二次除菌の推奨レジメンは、標準量PPIまたはVPZ 20 mg、AMPC 750 mg、MNZ 250 mgを1日2回・1週間投与するもので、PPIとVPZで除菌率は同等とされる。 | F8: JP | G8: 医学各論 Ⅻ-2-B-⑧（ヘリコバクター・ピロリ感染症、a） | J8: JSGE PUD GL 2026 | K8: 10.1007/s00535-026-02504-3 | M8: OPEN | N8: draft | P8: 2026-10-10 | Q8: 用量は保険診療上の用法と照合を要確認
A9: HP-008 | B9: 消化器 | C9: HP | E9: 欧州のMaastricht VI/Florenceコンセンサスは、感受性が不明な場合やCAM耐性率が15%を超える地域では、経験的一次治療として14日間のビスマス4剤療法を推奨している。 | F9: EU | G9: 医学各論 Ⅻ-2-B-⑧（ヘリコバクター・ピロリ感染症、a） | J9: Malfertheiner P et al. Gut 2022;71:1724-62 | K9: 10.1136/gutjnl-2022-327745 | L9: 35944925 | M9: RESTRICTED | N9: draft | P9: 2026-10-10 | Q9: 推奨文の詳細は二次文献（Microbiota journal 2023 review）経由。原著で要確認
A10: HP-009 | B10: 消化器 | C10: HP | E10: 米国ACG 2024は、未治療例の選択肢として最適化ビスマス4剤療法を優先し、感受性が確認されない限りCAMやレボフロキサシンを含むレジメンは避けるよう求めている。 | F10: US | G10: 医学各論 Ⅻ-2-B-⑧（ヘリコバクター・ピロリ感染症、a） | J10: Chey WD et al. Am J Gastroenterol 2024;119:1730-53（要旨はJCAG誌の解説（CC BY）経由） | K10: 10.14309/ajg.0000000000002968 | M10: RESTRICTED | N10: draft | P10: 2026-10-10
A11: HP-010 | B11: 消化器 | C11: HP | E11: ACG 2024は、未治療例の選択肢として、ビスマス4剤のほか、リファブチン三剤、VPZ＋AMPC二剤、VPZ三剤（いずれも14日間）を挙げている。 | F11: US | G11: 医学各論 Ⅻ-2-B-⑧（ヘリコバクター・ピロリ感染症、a） | J11: JCAG 2025 commentary（academic.oup.com/jcag/article/8/3/85/8125707） | M11: OPEN | N11: draft | P11: 2026-10-10
A12: HP-011 | B12: 消化器 | C12: HP | E12: PPI服用中は尿素呼気試験、迅速ウレアーゼ試験、ペプシノゲン値の信頼性が下がるため、診断にはこれらを用いない。 | F12: JP | G12: 医学各論 Ⅻ-2-B-⑧（ヘリコバクター・ピロリ感染症、a） | J12: JSHR GL 2024 英語版 | K12: 10.1007/s00535-026-02379-4 | M12: OPEN | N12: draft | P12: 2026-10-10
A13: HP-012 | B13: 消化器 | C13: HP | E13: 除菌判定の検査前には、PPIを2週間以上、ビスマスと抗菌薬を4週間以上中止し、治療終了から4週間以上あけて判定する。 | F13: US | G13: 医学各論 Ⅻ-2-B-⑧（ヘリコバクター・ピロリ感染症、a） | J13: ACG 2024（Emory大学の要約資料経由） | K13: 10.14309/ajg.0000000000002968 | M13: RESTRICTED | N13: draft | P13: 2026-10-10 | Q13: 日本のJSHR推奨期間との異同を要確認
A14: HP-013 | B14: 消化器 | C14: HP | E14: 尿素呼気試験のカットオフは除菌前で2.5〜3.5‰、除菌後で3.5〜4.0‰が適切とされ、除菌前に2.5‰を用いた場合の感度は96.2〜100%、特異度は83.3〜100%と報告されている。 | F14: JP | G14: 医学各論 Ⅻ-2-B-⑧（ヘリコバクター・ピロリ感染症、a） | J14: JSHR GL 2024 英語版 | K14: 10.1007/s00535-026-02379-4 | M14: OPEN | N14: draft | P14: 2026-10-10
A15: HP-014 | B15: 消化器 | C15: HP | E15: 京都分類に基づく内視鏡所見のうち、現感染を最も強く示すのはびまん性発赤（診断オッズ比26.8）で、粘膜腫脹13.3、白濁粘液10.2、皺襞腫大8.6が続く。 | F15: JP | G15: 医学各論 Ⅻ-2-B-⑧（ヘリコバクター・ピロリ感染症、a） | J15: Yoshii S et al. Dig Endosc 2020;32:74-83（JSHR GL 2024で引用） | K15: 10.1007/s00535-026-02379-4（引用元） | M15: UNKNOWN | N15: draft | P15: 2026-10-10 | Q15: RACに関する誤解例は専門医確認を要する
A16: HP-015 | B16: 消化器 | C16: HP | E16: JSHR 2024は、H. pylori感染症はすべて除菌の適応であるという基本方針を維持している。 | F16: JP | G16: 医学各論 Ⅻ-2-B-⑧（ヘリコバクター・ピロリ感染症、a） | J16: JSHR GL 2024 英語版（抄録） | K16: 10.1007/s00535-026-02379-4 | M16: OPEN | N16: draft | P16: 2026-10-10
A17: HP-016 | B17: 消化器 | C17: HP | E17: 胃癌予防の観点からは、より若い年齢での除菌が推奨され、日本では中学生の時期での検査と除菌が予防戦略として強調されている。 | F17: JP | G17: 医学各論 Ⅻ-2-B-⑧（ヘリコバクター・ピロリ感染症、a） | J17: JSHR GL 2024 英語版 | K17: 10.1007/s00535-026-02379-4 | M17: OPEN | N17: draft | P17: 2026-10-10 | Q17: 推奨の強さとエビデンスレベルは要確認
A18: HP-017 | B18: 消化器 | C18: HP | E18: 京都グローバルコンセンサスは、H. pylori胃炎を症状の有無にかかわらず感染症として位置づけた。 | F18: global | G18: 医学各論 Ⅻ-2-B-⑧（ヘリコバクター・ピロリ感染症、a） | J18: Sugano K et al. Gut 2015;64:1353-67 | K18: 10.1136/gutjnl-2015-309252 | L18: 26187502 | M18: RESTRICTED | N18: draft | P18: 2026-10-10 | Q18: 『症状の有無にかかわらず』の表現は原著で要確認
A19: HP-018 | B19: 消化器 | C19: HP | E19: 日本の胃潰瘍患者数は2023年に年間19.4万人、十二指腸潰瘍は2.0万人まで減少し、40年前と比べるとそれぞれ約10分の1、約20分の1になった。 | F19: JP | G19: 医学各論 Ⅻ-2-B-⑧（ヘリコバクター・ピロリ感染症、a） | J19: 厚労省 患者調査2023（JSGE PUD GL 2026の序論で引用） | M19: UNKNOWN | N19: draft | P19: 2026-10-10
A20: HP-019 | B20: 消化器 | C20: HP | E20: H. pylori陰性かつNSAID非使用の消化性潰瘍（特発性潰瘍）と、非H. pyloriヘリコバクター（NHPH）感染による潰瘍の増加が注目されている。 | F20: JP | G20: 医学各論 Ⅻ-2-B-⑧（ヘリコバクター・ピロリ感染症、a） | J20: JSGE PUD GL 2026（抄録） | K20: 10.1007/s00535-026-02504-3 | M20: OPEN | N20: draft | P20: 2026-10-10
A21: HP-020 | B21: 消化器 | C21: HP | E21: H. pylori陽性の限局期胃MALTリンパ腫では、除菌療法が一次治療として位置づけられている。 | F21: JP/EU | G21: 医学各論 Ⅻ-2-B-⑧（ヘリコバクター・ピロリ感染症、a） | J21: JSHR GL 2024（除菌適応疾患の一覧）／Maastricht VI | M21: RESTRICTED | N21: draft | P21: 2026-10-10 | Q21: 該当CQ番号、寛解率の数値、t(11;18)陽性例の扱いは要確認。完全寛解率の一次ソース（メタ解析PMID）は未取得
A22: UG-001 | B22: 消化器 | C22: UG | E22: 救急外来を受診した上部消化管出血のうち、院内での介入または死亡の見逃し率が1%以下となる超低リスク例（例：Glasgow-Blatchfordスコア0〜1）は、入院させず外来フォローで帰宅させることが提案されている。 | F22: US | J22: Laine L et al. Am J Gastroenterol 2021;116:899-917 | K22: 10.14309/ajg.0000000000001245 | L22: 33929377 | M22: RESTRICTED | N22: draft | P22: 2026-10-10
A23: UG-002 | B23: 消化器 | C23: UG | E23: GBS 0の感度の点推定値は99〜100%だが、特異度は8〜22%と低い。 | F23: US | J23: ACG 2021 | K23: 10.14309/ajg.0000000000001245 | M23: RESTRICTED | N23: draft | P23: 2026-10-10
A24: UG-003 | B24: 消化器 | C24: UG | E24: 上部消化管出血の入院患者では、Hb 7 g/dLを閾値とする制限輸血が提案されている。 | F24: US | J24: ACG 2021 | K24: 10.14309/ajg.0000000000001245 | M24: RESTRICTED | N24: draft | P24: 2026-10-10 | Q24: 心血管疾患合併例の具体的な閾値（8 g/dL等）は要確認
A25: UG-004 | B25: 消化器 | C25: UG | E25: 閾値7 g/dLの根拠となった上部消化管出血のRCT（単施設、n=921：制限群461例＜7 g/dL、非制限群460例＜9 g/dL）では、輸血を受けた患者の割合が制限群49%、非制限群86%（P<0.001）で、45日死亡率は5% vs 9%（HR 0.55; 95% CI 0.33–0.92）だった。 | F25: EU(Spain, Hospital de Sant Pau, Barcelona) | J25: Villanueva C et al. N Engl J Med 2013;368(1):11-21（ACG 2021が引用） | L25: 23281973 | M25: RESTRICTED | N25: draft | P25: 2026-10-10 | Q25: PMIDはPubMedの検索結果で確認。DOIは要確認｜［取り込み時］DOIは原本で「要確認」のためnull
A26: UG-005 | B26: 消化器 | C26: UG | E26: システマティックレビューでは、制限輸血によって輸血を受ける患者数が43%減り、臨床的に重要な転帰の悪化は認められなかった。 | F26: global | J26: ACG 2021 | K26: 10.14309/ajg.0000000000001245 | M26: RESTRICTED | N26: draft | P26: 2026-10-10
A27: UG-006 | B27: 消化器 | C27: UG | E27: 非静脈瘤性上部消化管出血では、循環動態を安定させた後、24時間以内に上部内視鏡を行うことが推奨される。 | F27: JP/EU/US | J27: JGES NVUGIB GL 第2版（強い推奨）、ESGE 2021、ACG 2021 | K27: 10.1111/den.15019; 10.1055/a-1369-5274 | M27: RESTRICTED | N27: draft | P27: 2026-10-10
A28: UG-007 | B28: 消化器 | C28: UG | E28: 上部消化管出血が疑われる患者に、スクリーニング目的で経鼻胃管をルーチンに挿入することは推奨されない。 | F28: JP | J28: JGES NVUGIB GL 第2版 | K28: 10.1111/den.15019 | M28: RESTRICTED | N28: draft | P28: 2026-10-10
A29: UG-008 | B29: 消化器 | C29: UG | E29: 重症または活動性出血が続く上部消化管出血では、内視鏡の30〜120分前にエリスロマイシン250 mgを単回静注することが推奨される。 | F29: EU | J29: ESGE 2015/2021、ESGE 2026 | K29: 10.1055/s-0034-1393172; 10.1055/a-2863-8314 | M29: UNKNOWN | N29: draft | P29: 2026-10-10 | Q29: 日本での保険適用外使用である点を要確認
A30: UG-009 | B30: 消化器 | C30: UG | E30: Forrest分類のIa（噴出性出血）、Ib（湧出性出血）、IIa（露出血管）は高リスク所見で内視鏡的止血の対象となる。IIc（平坦な色素斑）とIII（清浄潰瘍底）は再出血リスクが低く、止血処置を要しない。 | F30: global | J30: ESGE 2015 (10.1055/s-0034-1393172)、ACG 2021 | M30: RESTRICTED | N30: draft | P30: 2026-10-10
A31: UG-010 | B31: 消化器 | C31: UG | E31: ESGE 2026は、高リスク所見（FIa・FIb）の消化性潰瘍出血に対し、再出血がより少ないことから、over-the-scope（OTS）クリップ単独を従来の併用療法に代わる一次治療として提案している。 | F31: EU | J31: ESGE 2026（PubMed抄録 PMID 42127996） | K31: 10.1055/a-2863-8314 | M31: UNKNOWN | N31: draft | P31: 2026-10-10
A32: UG-011 | B32: 消化器 | C32: UG | E32: エピネフリン局注のみによる止血は不十分で、他の止血法と併用すべきである。 | F32: global | J32: ESGE 2021／ACG 2021 | M32: RESTRICTED | N32: draft | P32: 2026-10-10 | Q32: 今回取得した資料では文言を確認できていない。要確認
A33: UG-012 | B33: 消化器 | C33: UG | E33: 出血性潰瘍の内視鏡的止血後にPPIを投与すると、再出血、輸血量、入院期間、手術の必要性が減る。用量や投与経路による効果差は乏しいとされる。 | F33: JP | J33: JSGE PUD GL 2026 | K33: 10.1007/s00535-026-02504-3 | M33: OPEN | N33: draft | P33: 2026-10-10
A34: UG-013 | B34: 消化器 | C34: UG | E34: 止血成功後の高リスク潰瘍では、VPZ 40 mgと高用量PPI持続静注（80 mgボーラス後8 mg/時を72時間）を比べた2つのRCTで、再出血率と死亡率に差がなかった。 | F34: Thailand RCT | J34: Geeratragool T et al. Gastroenterology 2024;167:778-87（JSGE 2026経由） | K34: 10.1007/s00535-026-02504-3（引用元） | M34: OPEN | N34: draft | P34: 2026-10-10
A35: UG-014 | B35: 消化器 | C35: UG | E35: 内視鏡治療を行った高リスク潰瘍出血では、高用量PPI（1日80 mg以上）を3日間投与した後、2週間は1日2回のPPIを続けることが提案されている。 | F35: US | J35: ACG 2021（Emory大学の要約資料経由） | K35: 10.14309/ajg.0000000000001245 | M35: RESTRICTED | N35: draft | P35: 2026-10-10 | Q35: 原文の推奨強度は要確認
A36: UG-015 | B36: 消化器 | C36: UG | E36: ESGE 2026は、再出血例にはOTSクリップでの再止血を考慮し、それも不成功なら経カテーテル動脈塞栓術（TAE）、TAEができない・不成功なら手術という順序を推奨している。 | F36: EU | J36: ESGE 2026 | K36: 10.1055/a-2863-8314 | M36: UNKNOWN | N36: draft | P36: 2026-10-10
A37: UG-016 | B37: 消化器 | C37: UG | E37: 心血管疾患の二次予防として低用量アスピリンを服用中の患者が消化性潰瘍出血を起こした場合、再出血リスクが低ければ、内視鏡直後からアスピリンを再開することが推奨される。 | F37: EU | J37: ESGE 2015 | K37: 10.1055/s-0034-1393172 | M37: UNKNOWN | N37: draft | P37: 2026-10-10 | Q37: 最新版での再開時期（即時／3日以内等）は要確認
A38: UG-017 | B38: 消化器 | C38: UG | E38: 抗凝固療法の継続が必要な患者では、血栓塞栓リスクに応じて、臨床的に可能になった時点でできるだけ早く抗凝固薬を再開することが推奨される。 | F38: EU | J38: ESGE 2026 | K38: 10.1055/a-2863-8314 | M38: UNKNOWN | N38: draft | P38: 2026-10-10
A39: UG-018 | B39: 消化器 | C39: UG | E39: 持続的な止血が得られた消化性潰瘍出血では、止血後24時間以内に経口摂取を始め、鉄欠乏や貧血があれば退院前に鉄補充を開始することが提案されている。 | F39: EU | J39: ESGE 2026 | K39: 10.1055/a-2863-8314 | M39: UNKNOWN | N39: draft | P39: 2026-10-10
A40: ES-001 | B40: 消化器 | C40: ES | D40: GERD・NERD・Barrett食道 | E40: 日本消化器病学会のGERD診療ガイドライン第3版（日本語版）は2021年4月に刊行され、GERDを逆流性食道炎（RE）と非びらん性逆流症（NERD）に分けた治療アルゴリズムを導入した。 | F40: 日本 | G40: 医学各論 Ⅵ-1-B-①（胃食道逆流症<GERD>、非びらん性胃食道逆流症<NERD>、a） | H40: PS-02-08-05 (id: JkxnuRY) | J40: Iwakiri K, et al. JSGE GERD guidelines 2021. J Gastroenterol 2022;57:267-285 | K40: 10.1007/s00535-022-01861-z | L40: 35226174 | M40: OPEN | N40: verified_sources | P40: 2026-10-10 | Q40: low
A41: ES-002 | B41: 消化器 | C41: ES | D41: GERD・NERD・Barrett食道 | E41: 日本では、P-CABのボノプラザンが2015年2月に初めて逆流性食道炎の治療薬として使えるようになった。 | F41: 日本 | G41: 医学各論 Ⅵ-1-B-①（胃食道逆流症<GERD>、非びらん性胃食道逆流症<NERD>、a） | H41: PS-02-08-05 (id: JkxnuRY) | J41: Iwakiri K, et al. JSGE GERD guidelines 2021. J Gastroenterol 2022;57:267-285 | K41: 10.1007/s00535-022-01861-z | L41: 35226174 | M41: OPEN | N41: verified_sources | P41: 2026-10-10 | Q41: low
A42: ES-003 | B42: 消化器 | C42: ES | D42: GERD・NERD・Barrett食道 | E42: 日本のGERDガイドライン2021は、重症逆流性食道炎（LA分類C・D）の初期治療と維持治療にボノプラザンを提案している。 | F42: 日本 | G42: 医学各論 Ⅵ-1-B-②（逆流性食道炎（備考：Barrett上皮、Barrett食道）、a） | H42: PS-02-08-05 (id: JkxnuRY)；TBL-02-07-030 (id: JlAKplE) | J42: Iwakiri K, et al. JSGE GERD guidelines 2021. J Gastroenterol 2022;57:267-285 | K42: 10.1007/s00535-022-01861-z | L42: 35226174 | M42: OPEN | N42: verified_sources | P42: 2026-10-10 | Q42: low（推奨の方向と用量をGL本文で照合）
A43: ES-004 | B43: 消化器 | C43: ES | D43: GERD・NERD・Barrett食道 | E43: 軽症逆流性食道炎（LA分類A・B）では、初期治療にボノプラザンまたはPPIを推奨している。維持治療はPPIを推奨し、ボノプラザンを提案としている。 | F43: 日本 | G43: 医学各論 Ⅵ-1-B-②（逆流性食道炎（備考：Barrett上皮、Barrett食道）、a） | H43: PS-02-08-05 (id: JkxnuRY)；TBL-02-07-030 (id: JlAKplE) | J43: Iwakiri K, et al. JSGE GERD guidelines 2021. J Gastroenterol 2022;57:267-285 | K43: 10.1007/s00535-022-01861-z | L43: 35226174 | M43: OPEN | N43: verified_sources | P43: 2026-10-10 | Q43: low
A44: ES-005 | B44: 消化器 | C44: ES | D44: GERD・NERD・Barrett食道 | E44: ロサンゼルス（LA）分類は、粘膜傷害の長さと広がりで重症度を分ける。粘膜ひだの間で連続しない5 mm以下の傷害をA、5 mm超をB、2条以上のひだにまたがり全周の75%未満のものをC、75%以上をDとする。 | F44: 国際 | G44: 医学各論 Ⅵ-1-B-②（逆流性食道炎（備考：Barrett上皮、Barrett食道）、a） | H44: PS-02-08-05 (id: JkxnuRY)；TBL-02-07-030 (id: JlAKplE) | J44: Lundell LR, et al. Gut 1999 | K44: 10.1136/gut.45.2.172 | L44: 10403727 | M44: RESTRICTED | N44: draft | P44: 2026-10-10 | Q44: medium（グレードの定義はPMCでは抄録しか読めず、本文で未照合）
A45: ES-006 | B45: 消化器 | C45: ES | D45: GERD・NERD・Barrett食道 | E45: 日本では、重症逆流性食道炎の基準としてLA分類のC・Dを用いる。 | F45: 日本 | G45: 医学各論 Ⅵ-1-B-②（逆流性食道炎（備考：Barrett上皮、Barrett食道）、a） | H45: PS-02-08-05 (id: JkxnuRY)；TBL-02-07-030 (id: JlAKplE) | J45: Iwakiri K, et al. JSGE GERD guidelines 2021. J Gastroenterol 2022;57:267-285 | K45: 10.1007/s00535-022-01861-z | L45: 35226174 | M45: OPEN | N45: verified_sources | P45: 2026-10-10 | Q45: low
A46: ES-007 | B46: 消化器 | C46: ES | D46: GERD・NERD・Barrett食道 | E46: 日本の成人における逆流性食道炎の有病率は約10%と推定されている。 | F46: 日本 | G46: 医学各論 Ⅵ-1-B-②（逆流性食道炎（備考：Barrett上皮、Barrett食道）、a） | H46: PS-02-08-05 (id: JkxnuRY)；TBL-02-07-030 (id: JlAKplE) | J46: Iwakiri K, et al. JSGE GERD guidelines 2021. J Gastroenterol 2022;57:267-285 | K46: 10.1007/s00535-022-01861-z | L46: 35226174 | M46: OPEN | N46: verified_sources | P46: 2026-10-10 | Q46: low（JSGE GERD GL 2021 の疫学の記載で照合。原典はGLの引用文献）
A47: ES-008 | B47: 消化器 | C47: ES | D47: GERD・NERD・Barrett食道 | E47: 24時間pH・インピーダンス検査は酸逆流と非酸逆流の両方を検出できる。内視鏡で所見のないNERDやPPI抵抗性の症例で、逆流と症状の関連を評価する手段になる。 | F47: 国際 | G47: 医学各論 Ⅵ-1-B-①（胃食道逆流症<GERD>、非びらん性胃食道逆流症<NERD>、a） | H47: PS-02-08-05 (id: JkxnuRY)；TBL-02-07-025 (id: JlAKpkw) | J47: Iwakiri K, et al. Evidence-based clinical practice guidelines for gastroesophageal reflux disease 2021. J Gastroenterol 2022;57:267-285 | K47: 10.1007/s00535-022-01861-z | L47: 35226174 | M47: OPEN | N47: verified_sources | P47: 2026-10-10 | Q47: low（GL本文で照合）
A48: ES-009 | B48: 消化器 | C48: ES | D48: GERD・NERD・Barrett食道 | E48: Lyon consensus 2.0では、酸分泌抑制薬を中止して行う逆流モニタリングで、酸曝露時間（AET）が6%を超えればGERDの確定的根拠、4%未満なら生理的範囲、4〜6%は判定保留とする。内視鏡ではLA分類B以上の逆流性食道炎も確定的根拠とされた。 | G48: 医学各論 Ⅵ-1-B-①（胃食道逆流症<GERD>、非びらん性胃食道逆流症<NERD>、a） | H48: PS-02-08-05 (id: JkxnuRY)；TBL-02-07-030 (id: JlAKplE) | I48: SRC-010 | J48: Gyawali CP, et al. Updates to the modern diagnosis of GERD: Lyon consensus 2.0. Gut 2024;73(2):361-371 | K48: 10.1136/gutjnl-2023-330616 | L48: 37734911 | M48: RESTRICTED | N48: draft | P48: 2026-10-10 | Q48: アジアでAET 4%超を確定閾値とする提案は、Wong & Chen, Gut Liver 2025（PMID 40905050）およびAliment Pharmacol Ther誌のレター（DOI 10.1111/apt.70755）による。Lyon 2.0本体のPMIDは未取得
A49: ES-010 | B49: 消化器 | C49: ES | D49: GERD・NERD・Barrett食道 | E49: PPIテスト（PPIを試験的に投与し、症状が改善するかで判断する方法）は低侵襲・低コストで実地診療に用いられるが、24時間pH検査を基準とした統合解析では感度0.78、特異度0.54と診断精度に限界がある。 | F49: 国際 | G49: 医学各論 Ⅵ-1-B-①（胃食道逆流症<GERD>、非びらん性胃食道逆流症<NERD>、a） | H49: PS-02-08-05 (id: JkxnuRY) | J49: Iwakiri K, et al. JSGE GERD guidelines 2021. J Gastroenterol 2022;57:267-285 | K49: 10.1007/s00535-022-01861-z | L49: 35226174 | M49: OPEN | N49: verified_sources | P49: 2026-10-10 | Q49: low（GL本文で照合）
A50: ES-011 | B50: 消化器 | C50: ES | D50: GERD・NERD・Barrett食道 | E50: JSGE 2021は、薬物治療に抵抗するGERDで逆流と症状の関連が確認できた場合に、逆流防止手術を選択肢としている。PPI抵抗性NERDでは、多チャンネルインピーダンス・pHモニタリングで症状と逆流の因果関係が示された場合に手術を提案している（弱い推奨）。 | F50: 日本 | G50: 医学各論 Ⅵ-1-B-①（胃食道逆流症<GERD>、非びらん性胃食道逆流症<NERD>、a） | H50: PS-02-08-05 (id: JkxnuRY)；TBL-02-07-033 (id: JlAKplQ) | J50: Iwakiri K, et al. JSGE GERD guidelines 2021. J Gastroenterol 2022;57:267-285 | K50: 10.1007/s00535-022-01861-z | L50: 35226174 | M50: OPEN | N50: verified_sources | P50: 2026-10-10 | Q50: low（GL本文で照合）
A51: ES-012 | B51: 消化器 | C51: ES | D51: GERD・NERD・Barrett食道 | E51: 日本では食道胃接合部を柵状血管の下端で定義し、Barrett食道を全周3 cm以上のLSBEとそれ以外のSSBEに分ける。組織学的な腸上皮化生は必須としない。 | F51: 日本 | G51: 医学各論 Ⅵ-1-B-②（逆流性食道炎（備考：Barrett上皮、Barrett食道）、a） | H51: PS-02-08-05 (id: JkxnuRY) | J51: Japanese Classification of Esophageal Cancer 12th ed. Part I. Esophagus 2024;21:179-215 | K51: 10.1007/s10388-024-01054-y | L51: 38568243 | M51: OPEN | N51: draft | P51: 2026-10-10 | Q51: medium
A52: ES-013 | B52: 消化器 | C52: ES | D52: GERD・NERD・Barrett食道 | E52: 米国ACG 2022は、Barrett食道の診断に二つの条件を求める。食道胃接合部より口側の円柱上皮が1 cm以上あること、そして生検で腸上皮化生を認めることである。 | F52: 米国 | G52: 医学各論 Ⅵ-1-B-②（逆流性食道炎（備考：Barrett上皮、Barrett食道）、a） | H52: PS-02-08-05 (id: JkxnuRY) | J52: Shaheen NJ, et al. ACG Barrett's Esophagus guideline. Am J Gastroenterol 2022;117:559-587 | K52: 10.14309/ajg.0000000000001680 | L52: 35354777 | M52: RESTRICTED | N52: verified_sources | P52: 2026-10-10 | Q52: medium
A53: ES-014 | B53: 消化器 | C53: ES | D53: GERD・NERD・Barrett食道 | E53: ACG 2022は、Barrett食道の癌への進展率を、異形成なし（NDBE）で年0.05〜0.2%程度、低異型度異形成（LGD）で年約0.7%と見積もっている。 | F53: 欧米 | G53: 医学各論 Ⅵ-1-B-②（逆流性食道炎（備考：Barrett上皮、Barrett食道）、a） | H53: PS-02-08-05 (id: JkxnuRY) | J53: Shaheen NJ, et al. ACG Barrett's Esophagus guideline. Am J Gastroenterol 2022;117:559-587 | K53: 10.14309/ajg.0000000000001680 | L53: 35354777 | M53: RESTRICTED | N53: verified_sources | P53: 2026-10-10 | Q53: low（GL本文で照合。本文の表記は「0.2%–0.05%」）
A54: ES-015 | B54: 消化器 | C54: ES | D54: GERD・NERD・Barrett食道 | E54: 日本では、Barrett食道から食道癌が発生するリスクは、報告例が少ないため明らかになっていない。 | F54: 日本 | G54: 医学各論 Ⅵ-1-B-②（逆流性食道炎（備考：Barrett上皮、Barrett食道）、a） | H54: PS-02-08-05 (id: JkxnuRY) | J54: Kitagawa Y, et al. JES Esophageal cancer practice guidelines 2022 part 1. Esophagus 2023;20:343-372 | K54: 10.1007/s10388-023-00993-2 | L54: 36933136 | M54: OPEN | N54: verified_sources | P54: 2026-10-10 | Q54: low
A55: ES-016 | B55: 消化器 | C55: ES | D55: GERD・NERD・Barrett食道 | E55: ACG 2022は、NDBEのサーベイランス間隔を長さで分けている。3 cm未満は5年ごと、3 cm以上は3年ごとである。 | F55: 米国 | G55: 医学各論 Ⅵ-1-B-②（逆流性食道炎（備考：Barrett上皮、Barrett食道）、a） | H55: PS-02-08-05 (id: JkxnuRY) | J55: Shaheen NJ, et al. ACG Barrett's Esophagus guideline. Am J Gastroenterol 2022;117:559-587 | K55: 10.14309/ajg.0000000000001680 | L55: 35354777 | M55: RESTRICTED | N55: verified_sources | P55: 2026-10-10 | Q55: low
A56: ES-017 | B56: 消化器 | C56: ES | D56: GERD・NERD・Barrett食道 | E56: ACGは、Barrett食道の生検について、炎症を制御してから2 cm間隔で4方向から系統的に行う方法（Seattle protocol）を標準としている。 | F56: 米国 | G56: 医学各論 Ⅵ-1-B-②（逆流性食道炎（備考：Barrett上皮、Barrett食道）、a） | H56: PS-02-08-05 (id: JkxnuRY) | J56: Shaheen NJ, et al. ACG Barrett's Esophagus guideline. Am J Gastroenterol 2022;117:559-587 | K56: 10.14309/ajg.0000000000001680 | L56: 35354777 | M56: RESTRICTED | N56: verified_sources | P56: 2026-10-10 | Q56: low
A57: ES-018 | B57: 消化器 | C57: ES | D57: 好酸球性食道炎（EoE） | E57: EoEは、次の三つがそろったときに診断する。食道の機能障害による症状があること、食道生検で上皮内の好酸球が15個/HPF以上（約60個/mm²）であること、好酸球増多をきたす他の疾患を除外したことである。 | F57: 国際 | G57: 医学各論 Ⅵ-5-A-②（消化管アレルギー、好酸球性胃腸炎、好酸球性食道炎、b） | H57: PS-02-08-05 (id: JkxnuRY) | J57: ACG Clinical Guideline: EoE. Am J Gastroenterol 2025 | K57: 10.14309/ajg.0000000000003194 | L57: 39745304 | M57: UNKNOWN | N57: verified_sources | P57: 2026-10-10 | Q57: low
A58: ES-019 | B58: 消化器 | C58: ES | D58: 好酸球性食道炎（EoE） | E58: 現在の国際診断基準では、PPIが効くことはEoEを除外する理由にならない。PPIはEoEの治療選択肢の一つとして扱われる。 | F58: 国際 | G58: 医学各論 Ⅵ-5-A-②（消化管アレルギー、好酸球性胃腸炎、好酸球性食道炎、b） | H58: PS-02-08-05 (id: JkxnuRY) | J58: Dellon ES, et al. Updated international consensus diagnostic criteria for eosinophilic esophagitis: proceedings of the AGREE conference. Gastroenterology 2018;155:1022-1033 | K58: 10.1053/j.gastro.2018.07.009 | L58: 30009819 | M58: RESTRICTED | N58: verified_sources | P58: 2026-10-10 | Q58: low（抄録で照合）
A59: ES-020 | B59: 消化器 | C59: ES | D59: 好酸球性食道炎（EoE） | E59: 日本の多施設研究では、上部消化管内視鏡130,013件のうちEoEは66例（0.051%）で、約38%は健診の内視鏡で見つかった。 | F59: 日本 | G59: 医学各論 Ⅵ-5-A-②（消化管アレルギー、好酸球性胃腸炎、好酸球性食道炎、b） | H59: PS-02-08-05 (id: JkxnuRY)；TBL-02-07-030 (id: JlAKplE) | J59: Clinical and endoscopic characteristics of EoE in Japan: a case-control study | K59: 10.5415/apallergy.2020.10.e16 | L59: 32411581 | M59: RESTRICTED | N59: draft | P59: 2026-10-10 | Q59: low
A60: ES-021 | B60: 消化器 | C60: ES | D60: 好酸球性食道炎（EoE） | E60: EoEの典型的な内視鏡所見は、輪状溝、縦走溝、白斑（滲出物）、浮腫で、狭窄を伴うこともある。これらはEREFSで点数化する。 | F60: 国際 | G60: 医学各論 Ⅵ-5-A-②（消化管アレルギー、好酸球性胃腸炎、好酸球性食道炎、b） | H60: PS-02-08-05 (id: JkxnuRY)；TBL-02-07-030 (id: JlAKplE) | J60: Hirano I, et al. Endoscopic assessment of the oesophageal features of eosinophilic oesophagitis: validation of a novel classification and grading system. Gut 2013;62:489-495 | K60: 10.1136/gutjnl-2011-301817 | L60: 22619364 | M60: RESTRICTED | N60: verified_sources | P60: 2026-10-10 | Q60: low（抄録で照合）
A61: ES-022 | B61: 消化器 | C61: ES | D61: 好酸球性食道炎（EoE） | E61: EoEの初期治療には、PPI、嚥下させる局所ステロイド、除去食療法の3つがある。治療目標の目安は、組織学的に好酸球15個/HPF未満である。 | F61: 国際 | G61: 医学各論 Ⅵ-5-A-②（消化管アレルギー、好酸球性胃腸炎、好酸球性食道炎、b） | H61: PS-02-08-05 (id: JkxnuRY) | J61: ACG Clinical Guideline: EoE. Am J Gastroenterol 2025 | K61: 10.14309/ajg.0000000000003194 | L61: 39745304 | M61: UNKNOWN | N61: draft | P61: 2026-10-10 | Q61: medium
A62: ES-023 | B62: 消化器 | C62: ES | D62: 好酸球性食道炎（EoE） | E62: 12歳以上の好酸球性食道炎で、デュピルマブ300mgの週1回皮下投与は、プラセボに比べ24週時の組織学的寛解率を高め、嚥下障害の症状スコアを改善した。 | G62: 医学各論 Ⅵ-5-A-②（消化管アレルギー、好酸球性胃腸炎、好酸球性食道炎、b） | H62: PS-02-08-05 (id: JkxnuRY) | I62: SRC-026 | J62: Dellon ES, et al. NEJM 2022;387:2317-2330 | K62: 10.1056/NEJMoa2205982 | L62: 36546624 | M62: RESTRICTED | N62: verified_sources | P62: 2026-10-10 | Q62: 本文未閲覧。症状スコアの数値は未確認
A63: ES-024 | B63: 消化器 | C63: ES | D63: 好酸球性食道炎（EoE） | E63: デュピルマブは米国FDAで2022年5月20日に12歳以上（体重40kg以上）のEoEに承認され、2024年1月に1〜11歳（体重15kg以上）へ適応が拡大された。日本では今回の調査でEoEへの承認の記録を確認できなかった。 | G63: 医学各論 Ⅵ-5-A-②（消化管アレルギー、好酸球性胃腸炎、好酸球性食道炎、b） | H63: PS-02-08-05 (id: JkxnuRY) | J63: デュピクセント 医薬品インタビューフォーム（2026年3月改訂 第20版）、サノフィ国内申請報道 | M63: RESTRICTED | N63: draft | P63: 2026-10-10 | Q63: PMDA添付文書の効能・効果欄を全文照合していない。FDA承認日は企業発表で確認したもので、米国政府資料では未照合
A64: ES-025 | B64: 消化器 | C64: ES | D64: 食道運動障害 | E64: Chicago分類v4.0では、アカラシアを、IRP中央値の異常と蠕動の完全消失で定義する。そのうえで、20%以上の嚥下で食道全体の同時加圧（PEP）を示すものをII型、PEPのないものをI型とする。 | F64: 国際 | G64: 医学各論 Ⅵ-1-A-①（食道アカラシア、b） | H64: PS-02-08-05 (id: JkxnuRY)；TBL-02-07-004 (id: JlAKpjc) | I64: SRC-011 | J64: Yadlapati R, et al. Chicago Classification v4.0. Neurogastroenterol Motil 2021;33:e14058 | K64: 10.1111/nmo.14058 | L64: 33373111 | M64: RESTRICTED | N64: draft | P64: 2026-10-10 | Q64: low
A65: ES-026 | B65: 消化器 | C65: ES | D65: 食道運動障害 | E65: III型アカラシアは、IRP中央値が異常で、20%以上の嚥下が早期・痙攣性収縮を示し、正常な蠕動を伴わないものである。 | F65: 国際 | G65: 医学各論 Ⅵ-1-A-①（食道アカラシア、b） | H65: PS-02-08-05 (id: JkxnuRY)；TBL-02-07-004 (id: JlAKpjc) | I65: SRC-011 | J65: Yadlapati R, et al. Chicago Classification v4.0. Neurogastroenterol Motil 2021;33:e14058 | K65: 10.1111/nmo.14058 | L65: 33373111 | M65: RESTRICTED | N65: draft | P65: 2026-10-10 | Q65: low
A66: ES-027 | B66: 消化器 | C66: ES | D66: 食道運動障害 | E66: Chicago分類v4.0は、HRMで判定が確定しない例（判定保留）では、錠剤を併用した時限バリウム食道造影（TBE）やFLIPを補助検査として用いるよう勧めている。 | F66: 国際 | G66: 医学各論 Ⅵ-1-A-①（食道アカラシア、b） | H66: PS-02-08-03 (id: JkxnuRQ)；TBL-02-07-004 (id: JlAKpjc) | I66: SRC-011 | J66: Yadlapati R, et al. Chicago Classification v4.0. Neurogastroenterol Motil 2021;33:e14058 | K66: 10.1111/nmo.14058 | L66: 33373111 | M66: RESTRICTED | N66: verified_sources | P66: 2026-10-10 | Q66: low（本文で照合）
A67: ES-028 | B67: 消化器 | C67: ES | D67: 食道運動障害 | E67: 遠位食道痙攣は、IRP中央値が正常で、20%以上の嚥下が早期収縮を示すものである。早期収縮の目安は遠位潜時（DL）4.5秒未満である。 | F67: 国際 | G67: 医学各論 Ⅵ-1-A-①（食道アカラシア、b） | H67: PS-02-08-05 (id: JkxnuRY)；TBL-02-07-004 (id: JlAKpjc) | I67: SRC-011 | J67: Yadlapati R, et al. Chicago Classification v4.0. Neurogastroenterol Motil 2021;33:e14058 | K67: 10.1111/nmo.14058 | L67: 33373111 | M67: RESTRICTED | N67: verified_sources | P67: 2026-10-10 | Q67: low（本文で照合：DL 4.5秒未満かつDCI 450以上を早期収縮とする）
A68: ES-029 | B68: 消化器 | C68: ES | D68: 食道運動障害 | E68: Chicago分類v4.0では、DCIが450〜8,000 mmHg·s·cmを正常収縮、100以上450未満を弱収縮、100未満を失敗収縮、8,000超を過収縮とする。遠位潜時（DL）が4.5秒未満でDCIが450以上の収縮を早期（攣縮性）収縮とする。 | G68: 医学各論 Ⅵ-1-A-①（食道アカラシア、b） | H68: PS-02-08-03 (id: JkxnuRQ)；TBL-02-07-004 (id: JlAKpjc) | I68: SRC-011 | J68: Yadlapati R, et al. Chicago Classification v4.0. Neurogastroenterol Motil 2021 | K68: 10.1111/nmo.14058 | L68: 33373111 | M68: RESTRICTED | N68: verified_sources | P68: 2026-10-10 | Q68: なし（閾値は本文で確認）
A69: ES-030 | B69: 消化器 | C69: ES | D69: 食道運動障害 | E69: 無効食道運動（IEM）は、IRPが正常で、70%超の嚥下が無効、または50%以上で蠕動が欠如するものである。IRPが正常で蠕動が完全に消失しているものは、収縮欠如とする。 | F69: 国際 | G69: 医学各論 Ⅵ-1-A-①（食道アカラシア、b） | H69: PS-02-08-05 (id: JkxnuRY)；TBL-02-07-004 (id: JlAKpjc) | I69: SRC-011 | J69: Yadlapati R, et al. Chicago Classification v4.0. Neurogastroenterol Motil 2021;33:e14058 | K69: 10.1111/nmo.14058 | L69: 33373111 | M69: RESTRICTED | N69: verified_sources | P69: 2026-10-10 | Q69: low
A70: ES-031 | B70: 消化器 | C70: ES | D70: 食道運動障害 | E70: Chicago分類v4.0は、オピオイドがIII型アカラシアと関連するとし、可能であればオピオイドを中止した状態でHRMを行うよう勧めている。EGJ流出路障害（EGJOO）の一部もオピオイド使用に関連する。 | G70: 医学各論 Ⅵ-1-A-①（食道アカラシア、b） | H70: PS-02-08-03 (id: JkxnuRQ)；TBL-02-07-004 (id: JlAKpjc) | I70: SRC-011 | J70: Chicago Classification v4.0（PMC8034247） | K70: 10.1111/nmo.14058 | L70: 33373111 | M70: RESTRICTED | N70: verified_sources | P70: 2026-10-10 | Q70: low（本文で照合）
A71: ES-032 | B71: 消化器 | C71: ES | D71: 食道運動障害 | E71: アカラシアでは、POEMは腹腔鏡下Heller筋層切開＋Dor噴門形成術に対して2年時の治療成功で非劣性を示した。逆流性食道炎はPOEM群で多かった。 | G71: 医学各論 Ⅵ-1-A-①（食道アカラシア、b） | H71: PS-02-08-05 (id: JkxnuRY)；TBL-02-07-004 (id: JlAKpjc) | I71: SRC-025 | J71: Werner YB, et al. NEJM 2019;381:2219-2229 | K71: 10.1056/NEJMoa1905380 | L71: 31800987 | M71: RESTRICTED | N71: verified_sources | P71: 2026-10-10 | Q71: 本文未閲覧のため数値は主張文に含めない
A72: ES-033 | B72: 消化器 | C72: ES | D72: 食道運動障害 | E72: 同じRCTでは、逆流性食道炎がPOEM群に多かった（3か月時57% vs 20%、2年時44% vs 29%）。重篤な有害事象はPOEM 2.7%、LHM 7.3%だった。 | F72: 欧州 | G72: 医学各論 Ⅵ-1-A-①（食道アカラシア、b） | H72: PS-02-08-05 (id: JkxnuRY)；TBL-02-07-004 (id: JlAKpjc) | I72: SRC-025 | J72: Werner YB, et al. POEM vs LHM. N Engl J Med 2019;381:2219-2229 | K72: 10.1056/NEJMoa1905380 | L72: 31800987 | M72: RESTRICTED | N72: verified_sources | P72: 2026-10-10 | Q72: low
A73: ES-034 | B73: 消化器 | C73: ES | D73: 食道運動障害 | E73: ACG 2020は、III型アカラシアには空気圧拡張術（PD）より有効な治療として、筋切開長を病変に合わせて延ばしたPOEM（tailored POEM）またはLHMを推奨している。III型はLESに限った治療では成績が劣り、長い筋切開が重要と考えられている。 | F73: 国際 | G73: 医学各論 Ⅵ-1-A-①（食道アカラシア、b） | H73: PS-02-08-04 (id: JkxnuRU)；TBL-02-07-004 (id: JlAKpjc) | J73: Vaezi MF, et al. ACG clinical guidelines: diagnosis and management of achalasia. Am J Gastroenterol 2020;115:1393-1411 | K73: 10.14309/ajg.0000000000000731 | L73: 32773454 | M73: RESTRICTED | N73: verified_sources | P73: 2026-10-10 | Q73: low（GL本文 Recommendation 9 で照合）
A74: ES-035 | B74: 消化器 | C74: ES | D74: 食道癌 | E74: 日本の食道癌は、2023年に25,889例（男性20,977例、女性4,912例）が診断され、2024年に10,638人（男性8,572人、女性2,066人）が死亡した。罹患・死亡とも男性が約4倍多い。 | G74: 医学各論 Ⅵ-1-C-①（食道癌、a） | H74: PS-03-04-14 (id: JkxnuYE) | I74: SRC-014 | J74: 国立がん研究センター がん情報サービス 食道（罹患2026年3月23日更新、死亡2026年1月7日更新） | M74: GOV_JP | N74: draft | P74: 2026-10-10 | Q74: ganjoho.jpの利用規約の確認が残る（数値の利用のみ）
A75: ES-036 | B75: 消化器 | C75: ES | D75: 食道癌 | E75: 2019年の日本の食道癌死亡数は11,619人（粗死亡率は人口10万人あたり9.4）で、悪性新生物による死亡の3.1%を占めた。年齢調整死亡率は男女とも低下傾向にある。 | F75: 日本 | G75: 食道癌 | H75: 要確認 | J75: Kitagawa Y, et al. JES Esophageal cancer practice guidelines 2022 part 1. Esophagus 2023;20:343-372 | K75: 10.1007/s10388-023-00993-2 | L75: 36933136 | M75: OPEN | N75: retired | O75: ES-035 | P75: 2026-10-10 | Q75: low
A76: ES-037 | B76: 消化器 | C76: ES | D76: 食道癌 | E76: 日本食道学会の全国調査（2013年治療の8,019例）では、男女比は約5.4:1だった。占居部位は胸部中部食道が約47%で最も多く、組織型は扁平上皮癌が約86%、腺癌が約7%だった。 | F76: 日本 | G76: 医学各論 Ⅵ-1-C-①（食道癌、a） | H76: PS-03-04-14 (id: JkxnuYE) | J76: Kitagawa Y, et al. JES Esophageal cancer practice guidelines 2022 part 1. Esophagus 2023;20:343-372 | K76: 10.1007/s10388-023-00993-2 | L76: 36933136 | M76: OPEN | N76: verified_sources | P76: 2026-10-10 | Q76: low
A77: ES-038 | B77: 消化器 | C77: ES | D77: 食道癌 | E77: 日本の食道扁平上皮癌の主な危険因子は喫煙と習慣的飲酒で、診断例の約9割に関わる。両者が重なるとリスクは相乗的に高まる。緑黄色野菜と果物の摂取は予防因子とされる。 | F77: 日本 | G77: 医学各論 Ⅵ-1-C-①（食道癌、a） | H77: PS-03-04-14 (id: JkxnuYE) | J77: Kitagawa Y, et al. JES Esophageal cancer practice guidelines 2022 part 1. Esophagus 2023;20:343-372 | K77: 10.1007/s10388-023-00993-2 | L77: 36933136 | M77: OPEN | N77: verified_sources | P77: 2026-10-10 | Q77: low
A78: ES-039 | B78: 消化器 | C78: ES | D78: 食道癌 | E78: 欧米では食道癌に占める腺癌の割合が増え、現在は半数以上を占める。腺癌の発生母地は、GERDによる慢性炎症から生じるBarrett上皮である。 | F78: 欧米 | G78: 医学各論 Ⅵ-1-C-①（食道癌、a） | H78: PS-03-04-14 (id: JkxnuYE) | J78: Kitagawa Y, et al. JES Esophageal cancer practice guidelines 2022 part 1. Esophagus 2023;20:343-372 | K78: 10.1007/s10388-023-00993-2 | L78: 36933136 | M78: OPEN | N78: verified_sources | P78: 2026-10-10 | Q78: low
A79: ES-040 | B79: 消化器 | C79: ES | D79: 食道癌 | E79: 飲酒で生じるアセトアルデヒドは、2009年にWHOの作業部会でGroup 1の発がん物質とされた。アルコールやアセトアルデヒドを代謝する能力に関わる遺伝要因（ALDH2の不活性型など）は、飲酒による発癌リスクを左右する。 | F79: 東アジア／日本 | G79: 医学各論 Ⅵ-1-C-①（食道癌、a） | H79: PS-03-04-14 (id: JkxnuYE) | J79: Kitagawa Y, et al. JES Esophageal cancer practice guidelines 2022 part 1. Esophagus 2023;20:343-372 | K79: 10.1007/s10388-023-00993-2 | L79: 36933136 | M79: OPEN | N79: verified_sources | P79: 2026-10-10 | Q79: low（GL本文で照合）
A80: ES-041 | B80: 消化器 | C80: ES | D80: 食道癌 | E80: 食道癌は、同時性・異時性の多重癌を伴うことが多い。 | F80: 日本 | G80: 医学各論 Ⅵ-1-C-①（食道癌、a） | H80: PS-03-04-14 (id: JkxnuYE) | J80: Kitagawa Y, et al. JES Esophageal cancer practice guidelines 2022 part 1. Esophagus 2023;20:343-372 | K80: 10.1007/s10388-023-00993-2 | L80: 36933136 | M80: OPEN | N80: verified_sources | P80: 2026-10-10 | Q80: low（GL本文で照合）
A81: ES-042 | B81: 消化器 | C81: ES | D81: 食道癌 | E81: ヨード染色では、正常な扁平上皮は褐色に染まり、癌や異形成は不染帯として描出される。多発ヨード不染帯は、食道癌・頭頸部癌のリスクが高いことを示す。 | F81: 日本 | G81: 食道癌 | H81: 要確認 | J81: 一次出典未取得（要補完） | M81: UNKNOWN | N81: retired | O81: ES-089 | P81: 2026-10-10 | Q81: medium
A82: ES-043 | B82: 消化器 | C82: ES | D82: 食道癌 | E82: 日本食道学会の拡大内視鏡分類では、微小血管を境界病変のType Aと癌のType Bに分ける。Type Bはさらに、ループ様構造が保たれるB1、ループが消失するB2、高度に拡張したB3に分ける。 | F82: 日本 | G82: 医学各論 Ⅵ-1-C-①（食道癌、a） | H82: PS-03-04-14 (id: JkxnuYE)；TBL-02-07-030 (id: JlAKplE) | J82: Japanese Classification of Esophageal Cancer 12th ed. Part I. Esophagus 2024;21:179-215 | K82: 10.1007/s10388-024-01054-y | L82: 38568243 | M82: OPEN | N82: draft | P82: 2026-10-10 | Q82: low
A83: ES-044 | B83: 消化器 | C83: ES | D83: 食道癌 | E83: B1はT1a-EP/LPM、B2はT1a-MM/T1b-SM1、B3はT1b-SM2以深に対応する。B1とB3の正診率は高いが、B2は深達度を深読みしやすい。 | F83: 日本 | G83: 医学各論 Ⅵ-1-C-①（食道癌、a） | H83: PS-03-04-14 (id: JkxnuYE) | J83: Japanese Classification of Esophageal Cancer 12th ed. Part I. Esophagus 2024;21:179-215 | K83: 10.1007/s10388-024-01054-y | L83: 38568243 | M83: OPEN | N83: draft | P83: 2026-10-10 | Q83: low
A84: ES-045 | B84: 消化器 | C84: ES | D84: 食道癌 | E84: 表在食道扁平上皮癌の内視鏡切除は、EP/LPMにとどまる病変が良い適応である。MM/SM1は相対的適応、SM2以深は原則として外科切除か化学放射線療法の対象となる。 | F84: 日本 | G84: 医学各論 Ⅵ-1-C-①（食道癌、a） | H84: PS-03-04-14 (id: JkxnuYE)；TBL-02-07-033 (id: JlAKplQ) | J84: Kitagawa Y, et al. JES Esophageal cancer practice guidelines 2022 part 1. Esophagus 2023;20:343-372 | K84: 10.1007/s10388-023-00993-2 | L84: 36933136 | M84: OPEN | N84: draft | P84: 2026-10-10 | Q84: low
A85: ES-046 | B85: 消化器 | C85: ES | D85: 食道癌 | E85: 食道ESDで全周の3/4を超える粘膜欠損が生じる場合は、術後狭窄の予防にステロイドを使うことが勧められる。長径5 cmを超える全周性病変はESDの適応外とされる。 | F85: 日本 | G85: 医学各論 Ⅵ-1-C-①（食道癌、a） | H85: PS-03-04-14 (id: JkxnuYE)；TBL-02-07-033 (id: JlAKplQ) | I85: SRC-006 | J85: Ishihara R, et al. JGES ESD/EMR guidelines for esophageal cancer. Dig Endosc 2020;32:452-493 | K85: 10.1111/den.13654 | L85: 32072683 | M85: RESTRICTED | N85: draft | P85: 2026-10-10 | Q85: low
A86: ES-047 | B86: 消化器 | C86: ES | D86: 食道癌 | E86: 内視鏡切除後の病理でpT1a-MMかつ脈管侵襲陽性、またはpT1b-SMだった場合は、追加治療として食道切除術か化学放射線療法を行う根拠がある。 | F86: 日本 | G86: 医学各論 Ⅵ-1-C-①（食道癌、a） | H86: PS-03-04-14 (id: JkxnuYE)；TBL-02-07-033 (id: JlAKplQ) | J86: Kitagawa Y, et al. JES Esophageal cancer practice guidelines 2022 part 1. Esophagus 2023;20:343-372 | K86: 10.1007/s10388-023-00993-2 | L86: 36933136 | M86: OPEN | N86: verified_sources | P86: 2026-10-10 | Q86: medium
A87: ES-048 | B87: 消化器 | C87: ES | D87: 食道癌 | E87: 病期分類には、日本食道学会の食道癌取扱い規約（現行12版）とUICC/AJCCのTNM分類がある。両者は異なるため、試験結果を読むときはどちらの分類のどの版を使ったかを確認する必要がある。 | F87: 日本／国際 | G87: 医学各論 Ⅵ-1-C-①（食道癌、a） | H87: PS-03-04-14 (id: JkxnuYE) | J87: Japanese Classification of Esophageal Cancer 12th ed. Part I. Esophagus 2024;21:179-215 | K87: 10.1007/s10388-024-01054-y | L87: 38568243 | M87: OPEN | N87: draft | P87: 2026-10-10 | Q87: medium
A88: ES-049 | B88: 消化器 | C88: ES | D88: 食道癌 | E88: 切除可能な局所進行食道扁平上皮癌の術前療法として、ドセタキセルを加えた3剤併用（DCF）はシスプラチン＋5-FU（CF）より全生存を改善した。CFに放射線を加えた群（CF-RT）はCFに対する生存上の優越性を示さなかった。登録は601例（2012年12月〜2018年7月、1:1:1割付）。 | G88: 医学各論 Ⅵ-1-C-①（食道癌、a） | H88: PS-03-04-14 (id: JkxnuYE) | I88: SRC-001 | J88: Kato K, et al. JCOG1109 NExT. Lancet 2024;404(10447):55-66 | K88: 10.1016/S0140-6736(24)00745-1 | L88: 38876133 | M88: RESTRICTED | N88: verified_sources | P88: 2026-10-10 | Q88: 有害事象の割合はニュース照合のみのため主張文に含めない
A89: ES-050 | B89: 消化器 | C89: ES | D89: 食道癌 | E89: JCOG1109の病理学的完全奏効（pCR）率は、CF＋放射線療法38.5%、DCF 19.8%、CF 2.0%だった。CRT群のpCR率の高さは全生存の改善につながらなかった。 | F89: 日本 | G89: 医学各論 Ⅵ-1-C-①（食道癌、a） | H89: PS-03-04-14 (id: JkxnuYE) | I89: SRC-001 | J89: Kato K, et al. JCOG1109 NExT. Lancet 2024;404:55-66 | K89: 10.1016/S0140-6736(24)00745-1 | L89: 38876133 | M89: RESTRICTED | N89: draft | P89: 2026-10-10 | Q89: medium
A90: ES-051 | B90: 消化器 | C90: ES | D90: 食道癌 | E90: 術前化学放射線療法と切除の後に病理学的残存病変がある食道癌・食道胃接合部癌で、術後ニボルマブはプラセボに比べて無病生存期間を延長した（中央値22.4か月対11.0か月）。最終解析の全生存は統計学的有意差に達しなかった。 | G90: 医学各論 Ⅵ-1-C-①（食道癌、a） | H90: PS-03-04-14 (id: JkxnuYE) | I90: SRC-002 | J90: Kelly RJ, et al. CheckMate 577. NEJM 2021;384:1191-1203。OS: JCO 2025;43(16_suppl):4000 | K90: 10.1056/NEJMoa2032125 | L90: 33789008 | M90: RESTRICTED | N90: verified_sources | P90: 2026-10-10 | Q90: PMIDは照合不能のため削除。OSの数値はASCO抄録（Kelly RJ, JCO 2025;43(16_suppl):4000, DOI 10.1200/JCO.2025.43.16_suppl.4000）で確認：中央値51.7対35.3か月、HR 0.85（95.87%CI 0.70–1.04）。5年OS 46%対41%は未確認
A91: ES-052 | B91: 消化器 | C91: ES | D91: 食道癌 | E91: 切除不能な進行・再発食道扁平上皮癌の一次治療で、ニボルマブ＋化学療法とニボルマブ＋イピリムマブは、化学療法単独に比べて全生存を延長した。 | G91: 医学各論 Ⅵ-1-C-①（食道癌、a） | H91: PS-03-04-14 (id: JkxnuYE) | I91: SRC-003 | J91: Doki Y, et al. CheckMate 648. NEJM 2022;386:449-462 | K91: 10.1056/NEJMoa2111380 | L91: 35108470 | M91: RESTRICTED | N91: verified_sources | P91: 2026-10-10 | Q91: low（抄録で照合）
A92: ES-053 | B92: 消化器 | C92: ES | D92: 食道癌 | E92: KEYNOTE-590試験（749例）では、一次治療としてのペムブロリズマブ＋化学療法が全生存を延長した。扁平上皮癌かつPD-L1 CPS 10以上の集団では、全生存期間の中央値が13.9か月 vs 8.8か月、ハザード比0.57だった。 | F92: 国際 | G92: 医学各論 Ⅵ-1-C-①（食道癌、a） | H92: PS-03-04-14 (id: JkxnuYE) | I92: SRC-004 | J92: Sun JM, et al. KEYNOTE-590. Lancet 2021;398:759-771 | K92: 10.1016/S0140-6736(21)01234-4 | L92: 34454674 | M92: RESTRICTED | N92: verified_sources | P92: 2026-10-10 | Q92: low
A93: ES-054 | B93: 消化器 | C93: ES | D93: 食道癌 | E93: 進行食道癌の一次治療で、ペムブロリズマブ＋化学療法はプラセボ＋化学療法より全生存を改善した。追跡中央値58.8か月での5年全生存率は10.6%対3.0%だった。 | G93: 医学各論 Ⅵ-1-C-①（食道癌、a） | H93: PS-03-04-14 (id: JkxnuYE) | I93: SRC-004 | J93: Metges JP, et al. KEYNOTE-590 5-year extended follow-up. ESMO Open 2025;10(12):105854（原著：Sun JM, Lancet 2021;398:759-771, PMID 34454674） | K93: 10.1016/j.esmoop.2025.105854 | L93: 41259897 | M93: RESTRICTED | N93: verified_sources | P93: 2026-10-10 | Q93: low（5年生存率は5年追跡論文の抄録で照合）
A94: ES-055 | B94: 消化器 | C94: ES | D94: 食道癌 | E94: 切除できない局所進行食道癌や、手術を望まない・耐えられないcStage II/IIIの症例では、根治的化学放射線療法が選択肢になる。その後に病変が遺残・再発した場合は、救済手術を検討する。 | F94: 日本 | G94: 医学各論 Ⅵ-1-C-①（食道癌、a） | H94: PS-03-04-14 (id: JkxnuYE) | J94: Kitagawa Y, et al. JES Esophageal cancer practice guidelines 2022 part 1. Esophagus 2023;20:343-372 | K94: 10.1007/s10388-023-00993-2 | L94: 36933136 | M94: OPEN | N94: verified_sources | P94: 2026-10-10 | Q94: medium
A95: ES-056 | B95: 消化器 | C95: ES | D95: 食道癌 | E95: 日本食道学会のガイドラインは、76歳以上の患者に推奨を当てはめるときは注意するよう求めている。 | F95: 日本 | G95: 医学各論 Ⅵ-1-C-①（食道癌、a） | H95: PS-03-04-14 (id: JkxnuYE) | J95: Kitagawa Y, et al. JES Esophageal cancer practice guidelines 2022 part 1. Esophagus 2023;20:343-372 | K95: 10.1007/s10388-023-00993-2 | L95: 36933136 | M95: OPEN | N95: verified_sources | P95: 2026-10-10 | Q95: low
A96: ES-057 | B96: 消化器 | C96: ES | D96: 食道静脈瘤・門脈圧亢進症 | E96: 臨床的に有意な門脈圧亢進症（CSPH）は、肝静脈圧較差（HVPG）10 mmHg以上で定義される。 | F96: 国際 | G96: 医学各論 Ⅵ-6-D-①（門脈圧亢進症、a） | H96: PS-02-08-05 (id: JkxnuRY) | J96: Kaplan DE, et al. AASLD Practice Guidance, portal hypertension and varices. Hepatology 2024;79:1180-1211 | K96: 10.1097/HEP.0000000000000647 | L96: 37870298 | M96: RESTRICTED | N96: verified_sources | P96: 2026-10-10 | Q96: low
A97: ES-058 | B97: 消化器 | C97: ES | D97: 食道静脈瘤・門脈圧亢進症 | E97: Baveno VIIとAASLD 2024は、CSPHのある代償性肝硬変に非選択的β遮断薬（NSBB）を勧めており、カルベジロールを優先する。目的は非代償化の予防にまで及ぶ。 | F97: 欧米 | G97: 医学各論 Ⅵ-6-D-①（門脈圧亢進症、a） | H97: PS-02-08-05 (id: JkxnuRY) | J97: Kaplan DE, et al. AASLD Practice Guidance, portal hypertension and varices. Hepatology 2024;79:1180-1211 | K97: 10.1097/HEP.0000000000000647 | L97: 37870298 | M97: RESTRICTED | N97: verified_sources | P97: 2026-10-10 | Q97: low（Baveno VII本文で照合。AASLD 2024は本文未照合）
A98: ES-059 | B98: 消化器 | C98: ES | D98: 食道静脈瘤・門脈圧亢進症 | E98: AASLD 2024は、門脈圧亢進症に用いるNSBBとしてカルベジロールを第一に勧め、維持量を1日6.25〜12.5 mgとしている。 | F98: 米国 | G98: 医学各論 Ⅵ-6-D-①（門脈圧亢進症、a） | H98: PS-02-08-05 (id: JkxnuRY) | J98: Kaplan DE, et al. AASLD Practice Guidance, portal hypertension and varices. Hepatology 2024;79:1180-1211 | K98: 10.1097/HEP.0000000000000647 | L98: 37870298 | M98: RESTRICTED | N98: draft | P98: 2026-10-10 | Q98: low
A99: ES-060 | B99: 消化器 | C99: ES | D99: 食道静脈瘤・門脈圧亢進症 | E99: AASLD 2024は、高リスク静脈瘤の一次予防としてNSBBとEVLの両方を認めるが、NSBBを優先する。EVLは、NSBBを使えない場合に行う。 | F99: 米国 | G99: 医学各論 Ⅵ-1-D-①（食道静脈瘤（備考：胃静脈瘤、BRTO）、a） | H99: PS-02-08-05 (id: JkxnuRY)；TBL-02-07-033 (id: JlAKplQ) | J99: Kaplan DE, et al. AASLD Practice Guidance, portal hypertension and varices. Hepatology 2024;79:1180-1211 | K99: 10.1097/HEP.0000000000000647 | L99: 37870298 | M99: RESTRICTED | N99: draft | P99: 2026-10-10 | Q99: low
A100: ES-061 | B100: 消化器 | C100: ES | D100: 食道静脈瘤・門脈圧亢進症 | E100: 日本の食道・胃静脈瘤内視鏡所見記載基準は、占居部位（L）、形態（F）、色調（C）、発赤所見（RC）、出血所見（BS）、粘膜所見（MF）の6項目で記載する。食道ではLs・Lm・Li、F0〜F3、Cw・Cb、RC0〜3（ミミズ腫れ・チェリーレッドスポット・血マメ）を用いる。 | G100: 医学各論 Ⅵ-1-D-①（食道静脈瘤（備考：胃静脈瘤、BRTO）、a） | H100: PS-02-08-05 (id: JkxnuRY)；TBL-02-07-030 (id: JlAKplE) | I100: SRC-017 | J100: 日本門脈圧亢進症学会 門脈圧亢進症取扱い規約 第3版（記載基準表を日消誌116(5):395、日内会誌103(5):1187で確認） | M100: RESTRICTED | N100: draft | P100: 2026-10-10 | Q100: 取扱い規約の最新版（第4版の有無）は要確認
...

Sheet 出典一覧
A1: 出典番号 | B1: 書誌 | C1: DOI | D1: PMID | E1: ライセンス区分 | F1: ライセンス表示 | G1: 使っているカード数
A2: SRC-001 | B2: Kato K, JCOG1109 | D2: 38876133 | E2: RESTRICTED | F2: 非CC | G2: =COUNTIF(カード一覧!$I$2:$I$3170,A2) -> 2
A3: SRC-002 | B3: Kelly RJ, CheckMate 577 | C3: 10.1056/NEJMoa2032125 | E3: RESTRICTED | F3: 非CC | G3: =COUNTIF(カード一覧!$I$2:$I$3170,A3) -> 1
A4: SRC-003 | B4: Doki Y, CheckMate 648 | C4: 10.1056/NEJMoa2111380 | E4: RESTRICTED | F4: 非CC | G4: =COUNTIF(カード一覧!$I$2:$I$3170,A4) -> 1
A5: SRC-004 | B5: Sun JM, KEYNOTE-590 | D5: 34454674 | E5: RESTRICTED | F5: 非CC | G5: =COUNTIF(カード一覧!$I$2:$I$3170,A5) -> 2
A6: SRC-005 | B6: Metges JP, KEYNOTE-590 5年 | E6: RESTRICTED | F6: CC BY-NC-ND 4.0（Crossref） | G6: =COUNTIF(カード一覧!$I$2:$I$3170,A6) -> 0
A7: SRC-006 | B7: Ishihara R, JGES食道ESD/EMR GL | E7: RESTRICTED | F7: Wiley規約（Crossref） | G7: =COUNTIF(カード一覧!$I$2:$I$3170,A7) -> 2
A8: SRC-007 | B8: de Franchis R, Baveno VII | E8: RESTRICTED | F8: Elsevier TDMのみ | G8: =COUNTIF(カード一覧!$I$2:$I$3170,A8) -> 2
A9: SRC-008 | B9: Gralnek IM, ESGE静脈瘤GL | D9: 36174643 | E9: UNKNOWN | F9: 未確認 | G9: =COUNTIF(カード一覧!$I$2:$I$3170,A9) -> 0
A10: SRC-009 | B10: Birk M, ESGE異物GL | D10: 26862844 | E10: UNKNOWN | F10: 未確認 | G10: =COUNTIF(カード一覧!$I$2:$I$3170,A10) -> 4
A11: SRC-010 | B11: Gyawali CP, Lyon 2.0 | C11: 10.1136/gutjnl-2023-330616 | E11: RESTRICTED | F11: CC BY-NC（WUSTLの記録） | G11: =COUNTIF(カード一覧!$I$2:$I$3170,A11) -> 1
A12: SRC-011 | B12: Yadlapati R, Chicago v4.0 | E12: UNKNOWN | F12: 未確認 | G12: =COUNTIF(カード一覧!$I$2:$I$3170,A12) -> 7
A13: SRC-012 | B13: Brooks PJ, Alcohol flushing response | C13: 10.1371/journal.pmed.1000050 | E13: OPEN | F13: CC BY | G13: =COUNTIF(カード一覧!$I$2:$I$3170,A13) -> 1
A14: SRC-013 | B14: Lewis SJ, ALDH2メタ解析 | D14: 16103445 | E14: RESTRICTED | F14: 非CC | G14: =COUNTIF(カード一覧!$I$2:$I$3170,A14) -> 0
A15: SRC-014 | B15: 国立がん研究センター がん統計 | E15: GOV_JP | F15: 元データは政府統計。サイトの規約は未確認 | G15: =COUNTIF(カード一覧!$I$2:$I$3170,A15) -> 1
A16: SRC-015 | B16: 診療報酬点数表 K653-6 | E16: GOV_JP | F16: 告示原本は未閲覧 | G16: =COUNTIF(カード一覧!$I$2:$I$3170,A16) -> 1
A17: SRC-016 | B17: 小野薬品・BMS 適正使用文書 | E17: RESTRICTED | F17: 企業資料 | G17: =COUNTIF(カード一覧!$I$2:$I$3170,A17) -> 1
A18: SRC-017 | B18: 門脈圧亢進症取扱い規約 第3版の記載基準 | E18: RESTRICTED | F18: 非CC | G18: =COUNTIF(カード一覧!$I$2:$I$3170,A18) -> 2
A19: SRC-018 | B19: Yoshiji H, 肝硬変GL 2020 | E19: UNKNOWN | F19: 種別は未確認 | G19: =COUNTIF(カード一覧!$I$2:$I$3170,A19) -> 24
A20: SRC-019 | B20: Verhoeven RHA, CheckMate 577 実臨床 | E20: UNKNOWN | F20: 未確認 | G20: =COUNTIF(カード一覧!$I$2:$I$3170,A20) -> 0
A21: SRC-020 | B21: Contini S, 腐食性傷害の総説 | E21: RESTRICTED | F21: CC BY-NC | G21: =COUNTIF(カード一覧!$I$2:$I$3170,A21) -> 2
A22: SRC-021 | B22: Cheng HT, 成人の腐食性物質摂取 | E22: OPEN | F22: CC BY | G22: =COUNTIF(カード一覧!$I$2:$I$3170,A22) -> 1
A23: SRC-022 | B23: Boerhaave Syndrome—Narrative Review | E23: OPEN | F23: CC BY 4.0 | G23: =COUNTIF(カード一覧!$I$2:$I$3170,A23) -> 3
A24: SRC-023 | B24: HSV/CMV食道共感染の症例と文献レビュー | E24: UNKNOWN | F24: 未確認 | G24: =COUNTIF(カード一覧!$I$2:$I$3170,A24) -> 1
A25: SRC-024 | B25: HSV vs CMV食道炎の内視鏡所見 | C25: 10.1097/MD.0000000000015845 | E25: UNKNOWN | F25: 未確認 | G25: =COUNTIF(カード一覧!$I$2:$I$3170,A25) -> 2
A26: SRC-025 | B26: Werner YB, POEM vs LHM | D26: 31800987 | E26: RESTRICTED | F26: 非CC | G26: =COUNTIF(カード一覧!$I$2:$I$3170,A26) -> 2
A27: SRC-026 | B27: Dellon ES, デュピルマブ EoE | D27: 36546624 | E27: RESTRICTED | F27: 非CC | G27: =COUNTIF(カード一覧!$I$2:$I$3170,A27) -> 1
A28: SRC-027 | B28: Villanueva C, 輸血戦略 | D28: 23281973 | E28: RESTRICTED | F28: 非CC | G28: =COUNTIF(カード一覧!$I$2:$I$3170,A28) -> 1
A29: SRC-028 | B29: Miwa H, et al. Evidence-based clinical practice guidelines for functional dyspepsia 2021. J Gastroenterol 2022;57:47-61 | C29: 10.1007/s00535-021-01843-7 | E29: UNKNOWN | F29: Open access, © 2022 The Author(s)（CC種別は出版社ページで未表示。Crossrefで要確認） | G29: =COUNTIF(カード一覧!$I$2:$I$3170,A29) -> 18
A30: SRC-029 | B30: Japanese Gastric Cancer Association. Japanese Gastric Cancer Treatment Guidelines 2021 (6th edition). Gastric Cancer 2023;26:1-25 | C30: 10.1007/s10120-022-01331-8 | E30: UNKNOWN | F30: Open access, © 2022 The Author(s)（CC種別はCrossrefで要確認） | G30: =COUNTIF(カード一覧!$I$2:$I$3170,A30) -> 2
A31: SRC-030 | B31: Japanese Gastric Cancer Association. Japanese gastric cancer treatment guidelines 2025 (7th edition). Gastric Cancer 2026;29:271-299 | C31: 10.1007/s10120-025-01698-4 | E31: UNKNOWN | F31: Open access, © 2026 The Author(s)（CC種別はCrossrefで要確認） | G31: =COUNTIF(カード一覧!$I$2:$I$3170,A31) -> 23
A32: SRC-031 | B32: Sugimoto M, et al. Evidence-based clinical practice guidelines for peptic ulcer disease 2026. J Gastroenterol 2026;61:1361-1381 | C32: 10.1007/s00535-026-02504-3 | E32: OPEN | F32: CC BY 4.0（パイロット時にCrossrefで確認） | G32: =COUNTIF(カード一覧!$I$2:$I$3170,A32) -> 14
A33: SRC-032 | B33: Hirota S, et al. English version of Japanese Clinical Practice Guidelines 2022 for gastrointestinal stromal tumor (GIST). Int J Clin Oncol 2024;29:647-680 | C33: 10.1007/s10147-024-02488-1 | D33: 38609732 | E33: UNKNOWN | F33: Open access, © 2024 The Author(s)（CC種別はCrossrefで要確認） | G33: =COUNTIF(カード一覧!$I$2:$I$3170,A33) -> 8
A34: SRC-033 | B34: Joensuu H, et al. Adjuvant imatinib for high-risk GI stromal tumor: analysis of a randomized trial. J Clin Oncol 2016;34:244-250 | C34: 10.1200/JCO.2015.62.9170 | D34: 26527782 | E34: RESTRICTED | F34: 非CC（ASCO） | G34: =COUNTIF(カード一覧!$I$2:$I$3170,A34) -> 1
A35: SRC-034 | B35: Janjigian YY, et al. CheckMate 649. Lancet 2021;398:27-40 | C35: 10.1016/S0140-6736(21)00797-2 | D35: 34102137 | E35: RESTRICTED | F35: 非CC（Elsevier） | G35: =COUNTIF(カード一覧!$I$2:$I$3170,A35) -> 1
A36: SRC-035 | B36: Shitara K, et al. SPOTLIGHT. Lancet 2023;401:1655-1668 | C36: 10.1016/S0140-6736(23)00620-7 | D36: 37068504 | E36: RESTRICTED | F36: 非CC（Elsevier） | G36: =COUNTIF(カード一覧!$I$2:$I$3170,A36) -> 1
A37: SRC-036 | B37: 国立がん研究センター がん情報サービス 胃（罹患2026-03-23更新、死亡2026-01-07更新、生存率2026-07-22更新） | E37: GOV_JP | F37: 元データは政府統計。サイト利用規約は要確認 | G37: =COUNTIF(カード一覧!$I$2:$I$3170,A37) -> 1
A38: SRC-037 | B38: 厚生労働省『がん予防重点健康教育及びがん検診実施のための指針』（平成28年2月改正）／厚労省がん検診ページ | E38: GOV_JP | F38: 政府標準利用規約（原文は要確認） | G38: =COUNTIF(カード一覧!$I$2:$I$3170,A38) -> 2
A39: SRC-038 | B39: アステラス製薬 適時開示（2024-07-29）：ゾルベツキシマブ 欧州CHMP販売承認勧告（国内承認日の記載あり） | E39: RESTRICTED | F39: 企業資料（非CC） | G39: =COUNTIF(カード一覧!$I$2:$I$3170,A39) -> 1
A40: SRC-039 | B40: Panzuto F, et al. ENETS 2023 guidance paper for gastroduodenal neuroendocrine tumours (NETs) G1-G3. J Neuroendocrinol 2023;35:e13306 | C40: 10.1111/jne.13306 | E40: UNKNOWN | F40: Open access, © 2023 The Authors（CC種別はCrossrefで要確認） | G40: =COUNTIF(カード一覧!$I$2:$I$3170,A40) -> 1
A41: SRC-040 | B41: Scarpellini E, et al. International consensus on the diagnosis and management of dumping syndrome. Nat Rev Endocrinol 2020;16:448-466 | C41: 10.1038/s41574-020-0357-5 | E41: OPEN | F41: CC BY 4.0（出版社ページで確認） | G41: =COUNTIF(カード一覧!$I$2:$I$3170,A41) -> 6
A42: SRC-041 | B42: 厚生労働省『アニサキスによる食中毒を予防しましょう』 | E42: GOV_JP | F42: 厚労省ウェブサイト利用規約（政府標準利用規約準拠と想定、原文は要確認） | G42: =COUNTIF(カード一覧!$I$2:$I$3170,A42) -> 3
A43: SRC-042 | B43: Sugiyama H, et al. Anisakiasis annual incidence and causative species, Japan, 2018-2019. Emerg Infect Dis 2022;28(10) | C43: 10.3201/eid2810.220627 | E43: UNKNOWN | F43: CDC刊行誌。記事ページにパブリックドメインの明示はなく未確認 | G43: =COUNTIF(カード一覧!$I$2:$I$3170,A43) -> 2
A44: SRC-043 | B44: Islam RS, et al. Gastric polyps: a review on clinical, endoscopic, histopathologic features and management decisions. Gastroenterol Hepatol (N Y) 2013 Oct | E44: RESTRICTED | F44: © Millennium Medical Publishing（非CC） | G44: =COUNTIF(カード一覧!$I$2:$I$3170,A44) -> 3
A45: SRC-044 | B45: 岩室雅也. 薬剤起因性胃粘膜病変の内視鏡診断. 日本消化器内視鏡学会雑誌 2025;67(4):281-288 | C45: 10.11280/gee.67.281 | E45: RESTRICTED | F45: © 日本消化器内視鏡学会（J-STAGE無料公開、非CC） | G45: =COUNTIF(カード一覧!$I$2:$I$3170,A45) -> 3
A46: SRC-045 | B46: Cook D, et al. Stress ulcer prophylaxis during invasive mechanical ventilation (REVISE). N Engl J Med 2024 | C46: 10.1056/NEJMoa2404245 | E46: RESTRICTED | F46: 非CC（NEJM） | G46: =COUNTIF(カード一覧!$I$2:$I$3170,A46) -> 1
A47: SRC-046 | B47: Rizwan MM, et al. Duodenal diverticulum and associated pancreatitis: case report with brief review of literature. World J Gastrointest Endosc 2011;3(3):62-63 | C47: 10.4253/wjge.v3.i3.62 | D47: 21455344 | E47: RESTRICTED | F47: CC BY-NC 4.0 | G47: =COUNTIF(カード一覧!$I$2:$I$3170,A47) -> 2
A48: SRC-047 | B48: Ergüder E, et al. Lemmel syndrome: a single-center cohort and diagnostic considerations. Turk J Surg 2026;42(2):214-219 | C48: 10.47717/turkjsurg.2026.2025-11-25 | E48: UNKNOWN | F48: © Galenos Publishing House（ライセンス種別は未確認） | G48: =COUNTIF(カード一覧!$I$2:$I$3170,A48) -> 1
A49: SRC-048 | B49: Nakase H, et al. Evidence-based clinical practice guidelines for inflammatory bowel disease 2020. J Gastroenterol 2021;56:489-526 | C49: 10.1007/s00535-021-01784-1 | E49: UNKNOWN | F49: Open access、© The Author(s)（記事ページにCC種別の表示なし。Crossrefで確認） | G49: =COUNTIF(カード一覧!$I$2:$I$3170,A49) -> 10
A50: SRC-049 | B50: Fukudo S, et al. Evidence-based clinical practice guidelines for irritable bowel syndrome 2020. J Gastroenterol 2021;56:193-217 | C50: 10.1007/s00535-020-01746-z | E50: UNKNOWN | F50: Open access、© The Author(s)（記事ページにCC種別の表示なし。Crossrefで確認） | G50: =COUNTIF(カード一覧!$I$2:$I$3170,A50) -> 10
A51: SRC-050 | B51: Ihara E, et al. Evidence-Based Clinical Guidelines for Chronic Constipation 2023. Digestion 2025;106:62-89 | C51: 10.1159/000540912 | D51: 39159626 | E51: RESTRICTED | F51: CC BY-NC（記事ページの許諾リンクの表示による） | G51: =COUNTIF(カード一覧!$I$2:$I$3170,A51) -> 9
A52: SRC-051 | B52: Tanaka S, et al. Evidence-based clinical practice guidelines for management of colorectal polyps. J Gastroenterol 2021;56:323-335 | C52: 10.1007/s00535-021-01776-1 | E52: UNKNOWN | F52: Open access、© The Author(s)（記事ページにCC種別の表示なし。Crossrefで確認） | G52: =COUNTIF(カード一覧!$I$2:$I$3170,A52) -> 11
A53: SRC-052 | B53: Kinugasa Y, et al. Japanese Society for Cancer of the Colon and Rectum (JSCCR) guidelines 2024 for the treatment of colorectal cancer. Int J Clin Oncol 2025;30:2410-2463 | C53: 10.1007/s10147-025-02899-8 | E53: UNKNOWN | F53: Open access、© The Author(s)（記事ページにCC種別の表示なし。Crossrefで確認） | G53: =COUNTIF(カード一覧!$I$2:$I$3170,A53) -> 8
A54: SRC-053 | B54: 国立がん研究センター がん情報サービス 大腸（罹患2026-03-23更新、死亡2026-01-07更新、生存率2026-07-22更新） | E54: GOV_JP | F54: 元データは政府統計。サイト利用規約は人間が確認 | G54: =COUNTIF(カード一覧!$I$2:$I$3170,A54) -> 2
A55: SRC-054 | B55: National Cancer Institute. Genetics of Colorectal Cancer (PDQ)–Health Professional Version（最終更新 2025-03-21） | E55: GOV_US | F55: 米国連邦政府著作物（PDQは原則パブリックドメイン。第三者の図表は除く） | G55: =COUNTIF(カード一覧!$I$2:$I$3170,A55) -> 3
A56: SRC-055 | B56: 難病情報センター『潰瘍性大腸炎（指定難病97）』（情報更新 令和7年11月） | E56: UNKNOWN | F56: © 公益財団法人 難病医学研究財団（利用規約は未確認） | G56: =COUNTIF(カード一覧!$I$2:$I$3170,A56) -> 3
A57: SRC-056 | B57: 難病情報センター『クローン病（指定難病96）』（情報更新 令和7年11月） | E57: UNKNOWN | F57: © 公益財団法人 難病医学研究財団（利用規約は未確認） | G57: =COUNTIF(カード一覧!$I$2:$I$3170,A57) -> 3
A58: SRC-057 | B58: Nagata N, et al. Guidelines for Colonic Diverticular Bleeding and Colonic Diverticulitis: Japan Gastroenterological Association. Digestion 2019;99(Suppl 1):1-26 | C58: 10.1159/000495282 | E58: RESTRICTED | F58: CC BY-NC-ND（記事ページの許諾リンクの表示による）、© 2019 JGA | G58: =COUNTIF(カード一覧!$I$2:$I$3170,A58) -> 10
A59: SRC-058 | B59: 厚生労働省『腸管出血性大腸菌Q&A』（最終改訂 令和3年12月17日） | E59: GOV_JP | F59: 厚労省ウェブサイト利用規約（政府標準利用規約準拠と想定、原文は人間が確認） | G59: =COUNTIF(カード一覧!$I$2:$I$3170,A59) -> 4
A60: SRC-059 | B60: 厚生労働省『カンピロバクター食中毒予防について（Q&A）』（最終改訂 令和8年5月27日） | E60: GOV_JP | F60: 厚労省ウェブサイト利用規約（政府標準利用規約準拠と想定、原文は人間が確認） | G60: =COUNTIF(カード一覧!$I$2:$I$3170,A60) -> 2
A61: SRC-060 | B61: 厚生労働省『ノロウイルスに関するQ&A』（最終改定 令和3年11月19日） | E61: GOV_JP | F61: 厚労省ウェブサイト利用規約（政府標準利用規約準拠と想定、原文は人間が確認） | G61: =COUNTIF(カード一覧!$I$2:$I$3170,A61) -> 4
A62: SRC-061 | B62: CDC. C. diff: Facts for Clinicians（2026-04-13更新） | E62: GOV_US | F62: 米国連邦政府著作物（第三者素材を除く） | G62: =COUNTIF(カード一覧!$I$2:$I$3170,A62) -> 4
A63: SRC-062 | B63: Johnson S, et al. IDSA/SHEA 2021 Focused Update Guidelines on Management of Clostridioides difficile Infection in Adults. Clin Infect Dis 2021;73:e1029-e1044 | C63: 10.1093/cid/ciab549 | E63: RESTRICTED | F63: © IDSA, All rights reserved（複製・翻案は事前許諾が必要と明記） | G63: =COUNTIF(カード一覧!$I$2:$I$3170,A63) -> 1
A64: SRC-063 | B64: NIDDK. Definition & Facts for Celiac Disease（最終レビュー 2020年10月） | E64: GOV_US | F64: 米国連邦政府著作物（第三者素材を除く） | G64: =COUNTIF(カード一覧!$I$2:$I$3170,A64) -> 3
A65: SRC-064 | B65: NIDDK. Definition & Facts of Hemorrhoids（最終レビュー 2016年10月） | E65: GOV_US | F65: 米国連邦政府著作物（第三者素材を除く） | G65: =COUNTIF(カード一覧!$I$2:$I$3170,A65) -> 1
A66: SRC-065 | B66: Tokushige K, et al. Evidence-based clinical practice guidelines for nonalcoholic fatty liver disease/nonalcoholic steatohepatitis 2020. J Gastroenterol 2021;56:951-963 | C66: 10.1007/s00535-021-01796-x | E66: OPEN | F66: CC BY 4.0（記事ページの表示） | G66: =COUNTIF(カード一覧!$I$2:$I$3170,A66) -> 12
A67: SRC-066 | B67: Rinella ME, et al. A multisociety Delphi consensus statement on new fatty liver disease nomenclature. J Hepatol 2023;79:1542-1556 | C67: 10.1016/j.jhep.2023.06.003 | E67: RESTRICTED | F67: CC BY-NC-ND 4.0（論文PDFの表示） | G67: =COUNTIF(カード一覧!$I$2:$I$3170,A67) -> 3
A68: SRC-067 | B68: 日本肝臓学会 Clinical Practice Guidelines for Hepatocellular Carcinoma 2021（英語版PDF、第1・2・3分冊） | E68: RESTRICTED | F68: © The Japan Society of Hepatology. All Rights Reserved | G68: =COUNTIF(カード一覧!$I$2:$I$3170,A68) -> 12
A69: SRC-068 | B69: 国立がん研究センター がん情報サービス 肝臓（罹患2026-03-23更新、死亡2026-01-07更新、生存率2026-07-22更新） | E69: GOV_JP | F69: 元データは政府統計。サイト利用規約は人間が確認 | G69: =COUNTIF(カード一覧!$I$2:$I$3170,A69) -> 2
A70: SRC-069 | B70: CDC. Clinical Overview of Hepatitis A（2025-08-29更新） | E70: GOV_US | F70: 米国連邦政府著作物（第三者素材を除く） | G70: =COUNTIF(カード一覧!$I$2:$I$3170,A70) -> 3
A71: SRC-070 | B71: CDC. Clinical Overview of Hepatitis B（2025-08-29更新） | E71: GOV_US | F71: 米国連邦政府著作物（第三者素材を除く） | G71: =COUNTIF(カード一覧!$I$2:$I$3170,A71) -> 5
A72: SRC-071 | B72: CDC. Clinical Overview of Hepatitis C（2025-08-29更新） | E72: GOV_US | F72: 米国連邦政府著作物（第三者素材を除く） | G72: =COUNTIF(カード一覧!$I$2:$I$3170,A72) -> 4
A73: SRC-072 | B73: 厚生労働省『E型肝炎に関するQ&A』 | E73: GOV_JP | F73: 厚労省ウェブサイト利用規約（政府標準利用規約準拠と想定、原文は人間が確認） | G73: =COUNTIF(カード一覧!$I$2:$I$3170,A73) -> 3
A74: SRC-073 | B74: MedlinePlus Genetics. Gilbert syndrome（最終更新 2012-02-01） | E74: GOV_US | F74: 米国連邦政府著作物（NLM。第三者素材を除く） | G74: =COUNTIF(カード一覧!$I$2:$I$3170,A74) -> 2
A75: SRC-074 | B75: Sugawara K, Nakayama N, Mochida S. Acute liver failure in Japan: definition, classification, and prediction of the outcome. J Gastroenterol 2012;47:849-861 | C75: 10.1007/s00535-012-0624-x | E75: UNKNOWN | F75: Open access、© The Author(s)（記事ページにCC種別の表示なし。Crossrefで確認） | G75: =COUNTIF(カード一覧!$I$2:$I$3170,A75) -> 4
A76: SRC-075 | B76: 厚生労働省健康局結核感染症課 事務連絡『愛知県における犬のエキノコックス症感染事例について（情報提供）』（平成26年4月8日） | E76: GOV_JP | F76: 厚労省ウェブサイト利用規約（政府標準利用規約準拠と想定、原文は人間が確認） | G76: =COUNTIF(カード一覧!$I$2:$I$3170,A76) -> 2
A77: SRC-076 | B77: 厚生労働省 指定難病93『原発性胆汁性胆管炎』概要・診断基準等 | E77: GOV_JP | F77: 厚労省 指定難病の概要・診断基準等（政府標準利用規約準拠と想定、原文は人間が確認） | G77: =COUNTIF(カード一覧!$I$2:$I$3170,A77) -> 5
A78: SRC-077 | B78: 厚生労働省 指定難病95『自己免疫性肝炎』概要・診断基準等 | E78: GOV_JP | F78: 厚労省 指定難病の概要・診断基準等（政府標準利用規約準拠と想定、原文は人間が確認） | G78: =COUNTIF(カード一覧!$I$2:$I$3170,A78) -> 5
A79: SRC-078 | B79: 厚生労働省 指定難病171『ウィルソン病』概要・診断基準等 | E79: GOV_JP | F79: 厚労省 指定難病の概要・診断基準等（政府標準利用規約準拠と想定、原文は人間が確認） | G79: =COUNTIF(カード一覧!$I$2:$I$3170,A79) -> 3
A80: SRC-079 | B80: 厚生労働省 指定難病91『バッド・キアリ症候群』概要・診断基準等 | E80: GOV_JP | F80: 厚労省 指定難病の概要・診断基準等（政府標準利用規約準拠と想定、原文は人間が確認） | G80: =COUNTIF(カード一覧!$I$2:$I$3170,A80) -> 2
A81: SRC-080 | B81: 厚生労働省 指定難病92『特発性門脈圧亢進症』概要・診断基準等 | E81: GOV_JP | F81: 厚労省 指定難病の概要・診断基準等（政府標準利用規約準拠と想定、原文は人間が確認） | G81: =COUNTIF(カード一覧!$I$2:$I$3170,A81) -> 2
A82: SRC-081 | B82: MedlinePlus Genetics. Hereditary hemochromatosis（最終更新 2019-02-01） | E82: GOV_US | F82: 米国連邦政府著作物（NLM。第三者素材を除く） | G82: =COUNTIF(カード一覧!$I$2:$I$3170,A82) -> 2
A83: SRC-082 | B83: MedlinePlus Genetics. Dubin-Johnson syndrome（最終更新 2018-08-01） | E83: GOV_US | F83: 米国連邦政府著作物（NLM。第三者素材を除く） | G83: =COUNTIF(カード一覧!$I$2:$I$3170,A83) -> 1
A84: SRC-083 | B84: MedlinePlus Genetics. Rotor syndrome（最終更新 2013-03-01） | E84: GOV_US | F84: 米国連邦政府著作物（NLM。第三者素材を除く） | G84: =COUNTIF(カード一覧!$I$2:$I$3170,A84) -> 1
A85: SRC-084 | B85: Tajiri K, Shimizu Y. Practical guidelines for diagnosis and early management of drug-induced liver injury. World J Gastroenterol 2008;14:6774-6785 | C85: 10.3748/wjg.14.6774 | E85: RESTRICTED | F85: CC BY-NC 4.0（記事ページの表示） | G85: =COUNTIF(カード一覧!$I$2:$I$3170,A85) -> 3
A86: SRC-085 | B86: 日本肝臓学会 肝炎診療ガイドライン作成委員会編『B型肝炎治療ガイドライン（第4版）簡易版』2022年6月 | E86: RESTRICTED | F86: © 日本肝臓学会（非CC） | G86: =COUNTIF(カード一覧!$I$2:$I$3170,A86) -> 5
A87: SRC-086 | B87: 厚生労働省 感染症法に基づく医師の届出基準『五類感染症 アメーバ赤痢』と発生届様式 | E87: GOV_JP | F87: 厚労省ウェブサイト利用規約（政府標準利用規約準拠と想定、原文は人間が確認） | G87: =COUNTIF(カード一覧!$I$2:$I$3170,A87) -> 2
A88: SRC-087 | B88: 急性膵炎診療ガイドライン改訂出版委員会（改訂出版責任者 高田忠敬）『急性膵炎診療ガイドライン2021（第5版）』2021年12月（日本肝胆膵外科学会サイト掲載PDF） | E88: RESTRICTED | F88: 学会・出版社の著作物（非CC） | G88: =COUNTIF(カード一覧!$I$2:$I$3170,A88) -> 12
A89: SRC-088 | B89: 日本消化器病学会. Evidence-based clinical practice guidelines for chronic pancreatitis 2021. J Gastroenterol 2022（著者・巻・頁はCrossrefで確定） | C89: 10.1007/s00535-022-01911-6 | E89: UNKNOWN | F89: Open access、© The Author(s)（記事ページにCC種別の表示なし。Crossrefで確認） | G89: =COUNTIF(カード一覧!$I$2:$I$3170,A89) -> 10
A90: SRC-089 | B90: Okusaka T, et al. Clinical Practice Guidelines for Pancreatic Cancer 2022 from the Japan Pancreas Society: a synopsis. Int J Clin Oncol 2023;28:493-511 | C90: 10.1007/s10147-023-02317-x | E90: UNKNOWN | F90: Open access、© The Author(s)（記事ページにCC種別の表示なし。Crossrefで確認） | G90: =COUNTIF(カード一覧!$I$2:$I$3170,A90) -> 6
A91: SRC-090 | B91: 国立がん研究センター がん情報サービス 膵臓（罹患2026-03-23更新、死亡2026-01-07更新、生存率2026-07-22更新） | E91: GOV_JP | F91: 元データは政府統計。サイト利用規約は人間が確認 | G91: =COUNTIF(カード一覧!$I$2:$I$3170,A91) -> 2
A92: SRC-091 | B92: 国立がん研究センター がん情報サービス 胆のう・胆管（罹患2026-03-23更新、死亡2026-01-07更新、生存率2026-07-22更新） | E92: GOV_JP | F92: 元データは政府統計。サイト利用規約は人間が確認 | G92: =COUNTIF(カード一覧!$I$2:$I$3170,A92) -> 2
A93: SRC-092 | B93: 厚生労働省 指定難病94『原発性硬化性胆管炎』概要・診断基準等 | E93: GOV_JP | F93: 厚労省 指定難病の概要・診断基準等（政府標準利用規約準拠と想定、原文は人間が確認） | G93: =COUNTIF(カード一覧!$I$2:$I$3170,A93) -> 4
A94: SRC-093 | B94: 厚生労働省 指定難病300『IgG4関連疾患』概要・診断基準等 | E94: GOV_JP | F94: 厚労省 指定難病の概要・診断基準等（政府標準利用規約準拠と想定、原文は人間が確認） | G94: =COUNTIF(カード一覧!$I$2:$I$3170,A94) -> 4
A95: SRC-094 | B95: 日本肝胆膵外科学会ほか編『TG18新基準掲載 急性胆管炎・胆嚢炎診療ガイドライン2018（第3版）』医学図書出版、2018（Minds掲載本文PDF） | E95: RESTRICTED | F95: 著作権は著者・出版社に帰属（Mindsは私的利用の範囲に限ると明記） | G95: =COUNTIF(カード一覧!$I$2:$I$3170,A95) -> 6
A96: SRC-095 | B96: National Cancer Institute. Pancreatic Neuroendocrine Tumors (Islet Cell Tumors) Treatment (PDQ)–Health Professional Version（最終更新 2025-05-09） | E96: GOV_US | F96: 米国連邦政府著作物（PDQは原則パブリックドメイン。第三者の図表は除く） | G96: =COUNTIF(カード一覧!$I$2:$I$3170,A96) -> 5
A97: SRC-096 | B97: Ohtsuka T, et al. International evidence-based Kyoto guidelines for the management of intraductal papillary mucinous neoplasm of the pancreas. Pancreatology 2024;24:255-270 | C97: 10.1016/j.pan.2023.12.009 | D97: 38182527 | E97: UNKNOWN | F97: 未確認（抄録のみ参照） | G97: =COUNTIF(カード一覧!$I$2:$I$3170,A97) -> 1
A98: SRC-097 | B98: Fujita N, et al. Evidence-based clinical practice guidelines for cholelithiasis 2021. J Gastroenterol 2023;58:801-833 | C98: 10.1007/s00535-023-02014-6 | E98: UNKNOWN | F98: Springer OA（記事ページでライセンス表示を確認できず。Crossrefで確認） | G98: =COUNTIF(カード一覧!$I$2:$I$3170,A98) -> 9
A99: SRC-098 | B99: National Cancer Institute. Gallbladder Cancer Treatment (PDQ)–Health Professional Version | E99: GOV_US | F99: 米国連邦政府著作物（PDQは原則パブリックドメイン。第三者の図表は除く） | G99: =COUNTIF(カード一覧!$I$2:$I$3170,A99) -> 3
A100: SRC-099 | B100: National Cancer Institute. Bile Duct Cancer (Cholangiocarcinoma) Treatment (PDQ)–Health Professional Version（最終更新 2025-03-28） | E100: GOV_US | F100: 米国連邦政府著作物（PDQは原則パブリックドメイン。第三者の図表は除く） | G100: =COUNTIF(カード一覧!$I$2:$I$3170,A100) -> 4
...

Sheet 出題基準の網羅
A1: 章 | B1: 章の名前 | C1: 大項目 | D1: 番号 | E1: 項目 | F1: レベル | G1: 有効なカード数 | H1: カード
A2: Ⅰ | B2: 先天異常、周産期の異常、成長・発達の異常 | C2: 妊娠の異常 | D2: Ⅰ-1-A-① | E2: 妊娠悪阻 | F2: a | G2: =COUNTIFS(カード一覧!$G$2:$G$3170,"*医学各論 "&D2&"（*",カード一覧!$N$2:$N$3170,"<>retired") -> 0 | H2: =IF(G2>0,"あり","なし") -> なし
A3: Ⅰ | B3: 先天異常、周産期の異常、成長・発達の異常 | C3: 妊娠の異常 | D3: Ⅰ-1-A-② | E3: 異所性妊娠 | F3: a | G3: =COUNTIFS(カード一覧!$G$2:$G$3170,"*医学各論 "&D3&"（*",カード一覧!$N$2:$N$3170,"<>retired") -> 0 | H3: =IF(G3>0,"あり","なし") -> なし
A4: Ⅰ | B4: 先天異常、周産期の異常、成長・発達の異常 | C4: 妊娠の異常 | D4: Ⅰ-1-A-③ | E4: 流産、切迫流産 | F4: a | G4: =COUNTIFS(カード一覧!$G$2:$G$3170,"*医学各論 "&D4&"（*",カード一覧!$N$2:$N$3170,"<>retired") -> 0 | H4: =IF(G4>0,"あり","なし") -> なし
A5: Ⅰ | B5: 先天異常、周産期の異常、成長・発達の異常 | C5: 妊娠の異常 | D5: Ⅰ-1-A-④ | E5: 胞状奇胎 | F5: b | G5: =COUNTIFS(カード一覧!$G$2:$G$3170,"*医学各論 "&D5&"（*",カード一覧!$N$2:$N$3170,"<>retired") -> 0 | H5: =IF(G5>0,"あり","なし") -> なし
A6: Ⅰ | B6: 先天異常、周産期の異常、成長・発達の異常 | C6: 妊娠の異常 | D6: Ⅰ-1-A-⑤ | E6: 頸管無力症 | F6: b | G6: =COUNTIFS(カード一覧!$G$2:$G$3170,"*医学各論 "&D6&"（*",カード一覧!$N$2:$N$3170,"<>retired") -> 0 | H6: =IF(G6>0,"あり","なし") -> なし
A7: Ⅰ | B7: 先天異常、周産期の異常、成長・発達の異常 | C7: 妊娠の異常 | D7: Ⅰ-1-A-⑥ | E7: 不育症、習慣流産 | F7: b | G7: =COUNTIFS(カード一覧!$G$2:$G$3170,"*医学各論 "&D7&"（*",カード一覧!$N$2:$N$3170,"<>retired") -> 1 | H7: =IF(G7>0,"あり","なし") -> あり
A8: Ⅰ | B8: 先天異常、周産期の異常、成長・発達の異常 | C8: 妊娠の異常 | D8: Ⅰ-1-B-① | E8: 妊娠高血圧症候群、子癇、HELLP症候群、加重型妊娠高血圧腎症 | F8: a | G8: =COUNTIFS(カード一覧!$G$2:$G$3170,"*医学各論 "&D8&"（*",カード一覧!$N$2:$N$3170,"<>retired") -> 0 | H8: =IF(G8>0,"あり","なし") -> なし
A9: Ⅰ | B9: 先天異常、周産期の異常、成長・発達の異常 | C9: 妊娠の異常 | D9: Ⅰ-1-B-② | E9: 早産、切迫早産 | F9: a | G9: =COUNTIFS(カード一覧!$G$2:$G$3170,"*医学各論 "&D9&"（*",カード一覧!$N$2:$N$3170,"<>retired") -> 0 | H9: =IF(G9>0,"あり","なし") -> なし
A10: Ⅰ | B10: 先天異常、周産期の異常、成長・発達の異常 | C10: 妊娠の異常 | D10: Ⅰ-1-B-③ | E10: 常位胎盤早期剝離 | F10: a | G10: =COUNTIFS(カード一覧!$G$2:$G$3170,"*医学各論 "&D10&"（*",カード一覧!$N$2:$N$3170,"<>retired") -> 0 | H10: =IF(G10>0,"あり","なし") -> なし
A11: Ⅰ | B11: 先天異常、周産期の異常、成長・発達の異常 | C11: 妊娠の異常 | D11: Ⅰ-1-B-④ | E11: 前置胎盤、癒着胎盤 | F11: a | G11: =COUNTIFS(カード一覧!$G$2:$G$3170,"*医学各論 "&D11&"（*",カード一覧!$N$2:$N$3170,"<>retired") -> 0 | H11: =IF(G11>0,"あり","なし") -> なし
A12: Ⅰ | B12: 先天異常、周産期の異常、成長・発達の異常 | C12: 妊娠の異常 | D12: Ⅰ-1-B-⑤ | E12: 多胎妊娠 | F12: b | G12: =COUNTIFS(カード一覧!$G$2:$G$3170,"*医学各論 "&D12&"（*",カード一覧!$N$2:$N$3170,"<>retired") -> 0 | H12: =IF(G12>0,"あり","なし") -> なし
A13: Ⅰ | B13: 先天異常、周産期の異常、成長・発達の異常 | C13: 妊娠の異常 | D13: Ⅰ-1-B-⑥ | E13: 前期破水 | F13: b | G13: =COUNTIFS(カード一覧!$G$2:$G$3170,"*医学各論 "&D13&"（*",カード一覧!$N$2:$N$3170,"<>retired") -> 0 | H13: =IF(G13>0,"あり","なし") -> なし
... A1483: ⅩⅢ | B1483: 生活環境因子・職業性因子による疾患 | C1483: 物理的原因・生活環境因子による障害 | D1483: ⅩⅢ-5-I-③ | E1483: 自然災害 | F1483: a | G1483: =COUNTIFS(カード一覧!$G$2:$G$3170,"*医学各論 "&D1483&"（*",カード一覧!$N$2:$N$3170,"<>retired") -> 0 | H1483: =IF(G1483>0,"あり","なし") -> なし

Sheet 説明
A1: 項目 | B1: 説明
A2: このファイルについて | B2: hm-cmed/cleanroom-facts の data/facts（カード）、data/sources（出典）、data/curriculum（出題基準）から作った一覧です。元データを変えても、このファイルは自動では更新されません（作り直す必要があります）。
A3: 件数の数え方 | B3: 「概要」と「出題基準の網羅」の件数は、「カード一覧」「出典一覧」を数える数式です。
A4: 有効と廃止 | B4: 状態（status）が retired のカードは廃止です。置き換え先の列に、統合・差し替え先のカードがあります。ID は再利用しません。
A5: 状態 | B5: draft：出典・数値の照合が未完了。verified_sources：識別子とライセンスを API で照合済み。verified_expert：専門医が監修済み（人だけが付けます）。
A6: ライセンス区分 | B6: OPEN（CC BY・CC0）、RESTRICTED（CC BY-NC・ND、出版社規約など）、GOV_JP（日本の公的資料）、GOV_US（米国連邦政府著作物）、UNKNOWN（未確認。RESTRICTED と同じ扱い）。
A7: 出題基準の網羅 | B7: カードの出題基準の欄に「医学各論 番号（」が含まれ、廃止でないカードを数えています。「作らない」とした項目は、別の章の既存カードに番号を足して受けています。
A8: 著作権 | B8: 主張文は出典の文言を写さず自作した文です。このファイルに論文やガイドラインの本文は含みません。
